Workbook

Sheet Rules
A1: IRC Section | B1: Plain English Summary | C1: Affects Industry | D1: Affects Entity Type | E1: QuickBooks Data Needed | F1: Alert Message Template | G1: Non-Accountant Explanation
A2: §168 | B2: (k)Special allowance for certain property (1)Additional allowance In the case of any qualified property— (A)the depreciation deduction provided by section 167(a) for the taxable year in which such property is placed in service shall include an allowance equal to 100 percent of the adjusted basis of the qualified property, and (B)the adjusted basis of the qualified property shall be reduced by the amount of such deduction before computing the amount otherwise allowable as a depreciation deduction under this chapter for such taxable year and any subsequent taxable year. (2)Qualified property For purposes of this subsection— (A)In general The term “qualified property” means property— (i) (I)to which this section applies which has a recovery period of 20 years or less, (II)which is computer software (as defined in section 167(f)(1)(B)) for which a deduction is allowable under section 167(a) without regard to this subsection, (III)which is water utility property, or [2] (IV)which is a qualified film or television production (as defined in subsection (d) of section 181) for which a deduction would have been allowable under section 181 without regard to subsections (a)(2) and (h) of such section or this subsection, (V)which is a qualified live theatrical production (as defined in subsection (e) of section 181) for which a deduction would have been allowable under section 181 without regard to subsections (a)(2) and (h) of such section or this subsection, and or [3] (VI)which is a qualified sound recording production (as defined in subsection (f) of section 181) for which a deduction would have been allowable under section 181 without regard to subsections (a)(2) and (h) of such section or this subsection, and (ii)the original use of which begins with the taxpayer or the acquisition of which by the taxpayer meets the requirements of clause (i) of subparagraph (E). (B)Certain property having longer production periods treated as qualified property (i)In general The term “qualified property” includes any property if such property— (I)meets the requirements of clauses (i) and (ii) of subparagraph (A), (II)has a recovery period of at least 10 years or is transportation property, (III)is subject to section 263A, and (IV)meets the requirements of clause (iii) of section 263A(f)(1)(B) (determined as if such clause also applies to property which has a long useful life (within the meaning of section 263A(f))). (ii)Transportation property For purposes of this subparagraph, the term “transportation property” means tangible personal property used in the trade or business of transporting persons or property. (iii)Application of subparagraph This subparagraph shall not apply to any property which is described in subparagraph (C). (C)Certain aircraft The term “qualified property” includes property— (i)which meets the requirements of subparagraph (A)(ii), (ii)which is an aircraft which is not a transportation property (as defined in subparagraph (B)(ii)) other than for agricultural or firefighting purposes, (iii)which is purchased and on which such purchaser, at the time of the contract for purchase, has made a nonrefundable deposit of the lesser of— (I)10 percent of the cost, or (II)$100,000, and (iv)which has— (I)an estimated production period exceeding 4 months, and (II)a cost exceeding $200,000. (D)Exception for alternative depreciation property The term “qualified property” shall not include any property to which the alternative depreciation system under subsection (g) applies, determined— (i)without regard to paragraph (7) of subsection (g) (relating to election to have system apply), and (ii)after application of section 280F(b) (relating to listed property with limited business use). (E)Special rules (i)Acquisition requirements An acquisition of property meets the requirements of this clause if— (I)such property was not used by the taxpayer at any time prior to such acquisition, and (II)the acquisition of such property meets the requirements of paragraphs (2)(A), (2)(B), (2)(C), and (3) of section 179(d). (ii)Syndication For purposes of subparagraph (A)(ii), if— (I)property is used by a lessor of such property and such use is the lessor’s first use of such property, (II)such property is sold by such lessor or any subsequent purchaser within 3 months after the date such property was originally placed in service (or, in the case of multiple units of property subject to the same lease, within 3 months after the date the final unit is placed in service, so long as the period between the time the first unit is placed in service and the time the last unit is placed in service does not exceed 12 months), and (III)the user of such property after the last sale during such 3-month period remains the same as when such property was originally placed in service, such property shall be treated as originally placed in service not earlier than the date of such last sale. (F)Coordination with section 280F For purposes of section 280F— (i)Automobiles In the case of a passenger automobile (as defined in section 280F(d)(5)) which is qualified property, the Secretary shall increase the limitation under section 280F(a)(1)(A)(i) by $8,000. (ii)Listed property The deduction allowable under paragraph (1) shall be taken into account in computing any recapture amount under section 280F(b)(2). (iii)Phase down In the case of a passenger automobile acquired by the taxpayer before September 28, 2017, and placed in service by the taxpayer after September 27, 2017, clause (i) shall be applied by substituting for “$8,000”— (I)in the case of an automobile placed in service during 2018, $6,400, and (II)in the case of an automobile placed in service during 2019, $4,800. (G)Deduction allowed in computing minimum tax For purposes of determining alternative minimum taxable income under section 55, the deduction under section 167 for qualified property shall be determined without regard to any adjustment under section 56. (H)Production placed in service For purposes of subparagraph (A)— (i)a qualified film or television production shall be considered to be placed in service at the time of initial release or broadcast, (ii)a qualified live theatrical production shall be considered to be placed in service at the time of the initial live staged performance, and (iii)a qualified sound recording production shall be considered to be placed in service at the time of initial release or broadcast. [(3)Repealed. Pub. L. 115–97, title I, § 13204(a)(4)(B)(ii), Dec. 22, 2017, 131 Stat. 2111] [(4)Repealed. Pub. L. 115–97, title I, § 12001(b)(13), Dec. 22, 2017, 131 Stat. 2094] (5)Special rules for certain plants bearing fruits and nuts (A)In general In the case of any specified plant which is planted or grafted by the taxpayer in the ordinary course of the taxpayer’s farming business (as defined in section 263A(e)(4)) during a taxable year for which the taxpayer has elected the application of this paragraph— (i)a depreciation deduction equal to 100 percent of the adjusted basis of such specified plant shall be allowed under section 167(a) for the taxable year in which such specified plant is so planted or grafted, and (ii)the adjusted basis of such specified plant shall be reduced by the amount of such deduction. (B)Specified plant For purposes of this paragraph, the term “specified plant” means— (i)any tree or vine which bears fruits or nuts, and (ii)any other plant which will have more than one crop or yield of fruits or nuts and which generally has a pre-productive period of more than 2 years from the time of planting or grafting to the time at which such plant begins bearing a marketable crop or yield of fruits or nuts. Such term shall not include any property which is planted or grafted outside of the United States. (C)Election revocable only with consent An election under this paragraph may be revoked only with the consent of the Secretary. (D)Additional depreciation may be claimed only once If this paragraph applies to any specified plant, such specified plant shall not be treated as qualified property in the taxable year in which placed in service. (E)Deduction allowed in computing minimum tax Rules similar to the rules of paragraph (2)(G) shall apply for purposes of this paragraph. [(6)Repealed. Pub. L. 119–21, title VII, § 70301(b)(1)(B), July 4, 2025, 139 Stat. 189] (7)Election out If a taxpayer makes an election under this paragraph with respect to any class of property for any taxable year, paragraphs (1) and (2)(F) shall not apply to any qualified property in such class placed in service during such taxable year. An election under this paragraph may be revoked only with the consent of the Secretary. [(8)Repealed. Pub. L. 119–21, title VII, § 70301(b)(1)(B), July 4, 2025, 139 Stat. 189] (9)Exception for certain property The term “qualified property” shall not include— (A)any property which is primarily used in a trade or business described in clause (iv) of section 163(j)(7)(A), or (B)any property used in a trade or business that has had floor plan financing indebtedness (as defined in paragraph (9) of section 163(j)), if the floor plan financing interest related to such indebtedness was taken into account under paragraph (1)(C) of such section. (10)Special rule for property placed in service during certain periods (A)In general In the case of qualified property placed in service by the taxpayer during the first taxable year ending after January 19, 2025, if the taxpayer elects to have this paragraph apply for such taxable year, paragraph (1)(A) shall be applied— (i)in the case of property which is not described in clause (ii), by substituting “40 percent” for “100 percent”, or (ii)in the case of property which is described in subparagraph (B) or (C) of paragraph (2), by substituting “60 percent” for “100 percent”. (B)Specified plants In the case of any specified plant planted or grafted by the taxpayer during the first taxable year ending after January 19, 2025, if the taxpayer elects to have this paragraph apply for such taxable year, paragraph (5)(A)(i) shall be applied by substituting “40 percent” for “100 percent”. (C)Form of election Any election under this paragraph shall be made at such time and in such form and manner as the Secretary may prescribe. | C2: =IFERROR(__xludf.DUMMYFUNCTION("GEMINI(""Summarize this IRC legal text in exactly 1 sentence for a non-tax professional. Keep it under 20 words. Text: ""&B2)"),"Businesses can immediately deduct 100% of the cost of certain qualified property in the first year.") -> Businesses can immediately deduct 100% of the cost of certain qualified property in the first year. | D2: =IFERROR(__xludf.DUMMYFUNCTION("GEMINI(""Based on this IRC rule, list 3-5 industries and 2-3 entity types this affects. Format as: Industries: [x,y,z] | Entities: [a,b,c]. Text: ""&B2)"),"Industries: [Motion Picture and Video, Sound Recording, Performing Arts, Agriculture, Transportation] | Entities: [Corporations, Limited Liability Companies, Partnerships]") -> Industries: [Motion Picture and Video, Sound Recording, Performing Arts, Agriculture, Transportation] | Entities: [Corporations, Limited Liability Companies, Partnerships] | E2: =IFERROR(__xludf.DUMMYFUNCTION("GEMINI(""What specific QuickBooks data fields must be checked to see if this IRC rule applies to a business? List them as comma-separated account names or report fields. Text: ""&B2)"),"Fixed Asset Accounts, Purchase Date, Asset Description, Original Cost, Accumulated Depreciation, Section 179/Bonus Depreciation Election, Chart of Accounts (for business type and floor plan financing interest), Vehicle Log (for 280F compliance), Item List"&" (for computer software or media productions)") -> Fixed Asset Accounts, Purchase Date, Asset Description, Original Cost, Accumulated Depreciation, Section 179/Bonus Depreciation Election, Chart of Accounts (for business type and floor plan financing interest), Vehicle Log (for 280F compliance), Item List (for computer software or media productions) | F2: 🚨 Important: 100% Bonus Depreciation Restoration for [Entity] How this affects you: Great news for [Date]\! Under the newly restored provisions of IRC Section 168(k), your business can now immediately deduct 100% of the cost of qualified property placed in service after January 19, 2025. This allows [Entity] to write off the full [Amount] of eligible investments—such as machinery, equipment, computer software, and certain vehicles—in a single year rather than over a standard depreciation schedule, significantly reducing your taxable income and improving immediate cash flow. ✅ Verify that the property meets the "original use" requirement or was newly acquired by your business ✅ Ensure the assets have a recovery period of 20 years or less to qualify for the full deduction ✅ Update your QuickBooks fixed asset records to reflect the 100% first-year allowance election 📚 Source: IRC Section 168 ⚠️ Disclaimer: This template is for informational purposes only. Tax laws are subject to change and eligibility criteria for qualified property are complex. Please consult with a qualified tax professional to confirm compliance for your specific situation. | G2: =IFERROR(__xludf.DUMMYFUNCTION("GEMINI(""Explain in 1 sentence how §168 impacts ratios like Effective Tax Rate or R&D Intensity. For a non-accountant CFO. Text: ""&B2)"),"IRC Section 168 provides an immediate 100% bonus depreciation deduction for qualified property, which lowers your taxable income and can significantly reduce your effective tax rate in the year assets are placed in service.") -> IRC Section 168 provides an immediate 100% bonus depreciation deduction for qualified property, which lowers your taxable income and can significantly reduce your effective tax rate in the year assets are placed in service.
A3: §179 | B3: (a)Treatment as expenses A taxpayer may elect to treat the cost of any section 179 property as an expense which is not chargeable to capital account. Any cost so treated shall be allowed as a deduction for the taxable year in which the section 179 property is placed in service. (b)Limitations (1)Dollar limitation The aggregate cost which may be taken into account under subsection (a) for any taxable year shall not exceed $2,500,000. (2)Reduction in limitation The limitation under paragraph (1) for any taxable year shall be reduced (but not below zero) by the amount by which the cost of section 179 property placed in service during such taxable year exceeds $4,000,000. (3)Limitation based on income from trade or business (A)In general The amount allowed as a deduction under subsection (a) for any taxable year (determined after the application of paragraphs (1) and (2)) shall not exceed the aggregate amount of taxable income of the taxpayer for such taxable year which is derived from the active conduct by the taxpayer of any trade or business during such taxable year. (B)Carryover of disallowed deduction The amount allowable as a deduction under subsection (a) for any taxable year shall be increased by the lesser of— (i)the aggregate amount disallowed under subparagraph (A) for all prior taxable years (to the extent not previously allowed as a deduction by reason of this subparagraph), or (ii)the excess (if any) of— (I)the limitation of paragraphs (1) and (2) (or if lesser, the aggregate amount of taxable income referred to in subparagraph (A)), over (II)the amount allowable as a deduction under subsection (a) for such taxable year without regard to this subparagraph. (C)Computation of taxable income For purposes of this paragraph, taxable income derived from the conduct of a trade or business shall be computed without regard to the deduction allowable under this section. (4)Married individuals filing separately In the case of a husband and wife filing separate returns for the taxable year— (A)such individuals shall be treated as 1 taxpayer for purposes of paragraphs (1) and (2), and (B)unless such individuals elect otherwise, 50 percent of the cost which may be taken into account under subsection (a) for such taxable year (before application of paragraph (3)) shall be allocated to each such individual. (5)Limitation on cost taken into account for certain passenger vehicles (A)In general The cost of any sport utility vehicle for any taxable year which may be taken into account under this section shall not exceed $25,000. (B)Sport utility vehicle For purposes of subparagraph (A)— (i)In general The term “sport utility vehicle” means any 4-wheeled vehicle— (I)which is primarily designed or which can be used to carry passengers over public streets, roads, or highways (except any vehicle operated exclusively on a rail or rails), (II)which is not subject to section 280F, and (III)which is rated at not more than 14,000 pounds gross vehicle weight. (ii)Certain vehicles excluded Such term does not include any vehicle which— (I)is designed to have a seating capacity of more than 9 persons behind the driver’s seat, (II)is equipped with a cargo area of at least 6 feet in interior length which is an open area or is designed for use as an open area but is enclosed by a cap and is not readily accessible directly from the passenger compartment, or (III)has an integral enclosure, fully enclosing the driver compartment and load carrying device, does not have seating rearward of the driver’s seat, and has no body section protruding more than 30 inches ahead of the leading edge of the windshield. (6)Inflation adjustment (A)In general In the case of any taxable year beginning after 2018 (2025 in the case of the dollar amounts in paragraphs (1) and (2)), the dollar amounts in paragraphs (1), (2), and (5)(A) shall each be increased by an amount equal to— (i)such dollar amount, multiplied by (ii)the cost-of-living adjustment determined under section 1(f)(3) for the calendar year in which the taxable year begins, determined by substituting in subparagraph (A)(ii) thereof— (I)in the case of amounts in paragraphs (1) and (2), “calendar year 2024” for “calendar year 2016”, and (II)in the case of the amount in paragraph (5)(A), “calendar year 2017” for “calendar year 2016”. (B)Rounding The amount of any increase under subparagraph (A) shall be rounded to the nearest multiple of $10,000 ($100 in the case of any increase in the amount under paragraph (5)(A)). (c)Election (1)In general An election under this section for any taxable year shall— (A)specify the items of section 179 property to which the election applies and the portion of the cost of each of such items which is to be taken into account under subsection (a), and (B)be made on the taxpayer’s return of the tax imposed by this chapter for the taxable year. Such election shall be made in such manner as the Secretary may by regulations prescribe. (2)Election Any election made under this section, and any specification contained in any such election, may be revoked by the taxpayer with respect to any property, and such revocation, once made, shall be irrevocable. (d)Definitions and special rules (1)Section 179 property For purposes of this section, the term “section 179 property” means property— (A)which is— (i)tangible property (to which section 168 applies), or (ii)computer software (as defined in section 197(e)(3)(B)) which is described in section 197(e)(3)(A)(i) and to which section 167 applies, (B)which is— (i)section 1245 property (as defined in section 1245(a)(3)), or (ii)at the election of the taxpayer, qualified real property (as defined in subsection (e)), and (C)which is acquired by purchase for use in the active conduct of a trade or business. Such term shall not include any property described in section 50(b) (other than paragraph (2) thereof). (2)Purchase defined For purposes of paragraph (1), the term “purchase” means any acquisition of property, but only if— (A)the property is not acquired from a person whose relationship to the person acquiring it would result in the disallowance of losses under section 267 or 707(b) (but, in applying section 267(b) and (c) for purposes of this section, paragraph (4) of section 267(c) shall be treated as providing that the family of an individual shall include only his spouse, ancestors, and lineal descendants), (B)the property is not acquired by one component member of a controlled group from another component member of the same controlled group, and (C)the basis of the property in the hands of the person acquiring it is not determined— (i)in whole or in part by reference to the adjusted basis of such property in the hands of the person from whom acquired, or (ii)under section 1014(a) (relating to property acquired from a decedent). (3)Cost For purposes of this section, the cost of property does not include so much of the basis of such property as is determined by reference to the basis of other property held at any time by the person acquiring such property. (4)Section not to apply to estates and trusts This section shall not apply to estates and trusts. (5)Section not to apply to certain noncorporate lessors This section shall not apply to any section 179 property which is purchased by a person who is not a corporation and with respect to which such person is the lessor unless— (A)the property subject to the lease has been manufactured or produced by the lessor, or (B)the term of the lease (taking into account options to renew) is less than 50 percent of the class life of the property (as defined in section 168(i)(1)), and for the period consisting of the first 12 months after the date on which the property is transferred to the lessee the sum of the deductions with respect to such property which are allowable to the lessor solely by reason of section 162 (other than rents and reimbursed amounts with respect to such property) exceeds 15 percent of the rental income produced by such property. (6)Dollar limitation of controlled group For purposes of subsection (b) of this section— (A)all component members of a controlled group shall be treated as one taxpayer, and (B)the Secretary shall apportion the dollar limitation contained in subsection (b)(1) among the component members of such controlled group in such manner as he shall by regulations prescribe. (7)Controlled group defined For purposes of paragraphs (2) and (6), the term “controlled group” has the meaning assigned to it by section 1563(a), except that, for such purposes, the phrase “more than 50 percent” shall be substituted for the phrase “at least 80 percent” each place it appears in section 1563(a)(1). (8)Treatment of partnerships and S corporations In the case of a partnership, the limitations of subsection (b) shall apply with respect to the partnership and with respect to each partner. A similar rule shall apply in the case of an S corporation and its shareholders. (9)Coordination with section 38 No credit shall be allowed under section 38 with respect to any amount for which a deduction is allowed under subsection (a). (10)Recapture in certain cases The Secretary shall, by regulations, provide for recapturing the benefit under any deduction allowable under subsection (a) with respect to any property which is not used predominantly in a trade or business at any time. (e)Qualified real property For purposes of this section, the term “qualified real property” means— (1)any qualified improvement property described in section 168(e)(6), and (2)any of the following improvements to nonresidential real property placed in service after the date such property was first placed in service: (A)Roofs. (B)Heating, ventilation, and air-conditioning property. (C)Fire protection and alarm systems. (D)Security systems. (Added Pub. L. 85–866, title II, § 204(a), Sept. 2, 1958, 72 Stat. 1679; amended Pub. L. 87–834, § 13(c)(2), Oct. 16, 1962, 76 Stat. 1034; Pub. L. 91–172, title IV, § 401(f), Dec. 30, 1969, 83 Stat. 603; Pub. L. 94–455, title II, § 213(a), title XIX, § 1906(b)(13)(A), Oct. 4, 1976, 90 Stat. 1547, 1834; Pub. L. 97–34, title II, § 202(a), Aug. 13, 1981, 95 Stat. 219; Pub. L. 97–354, § 3(f), Oct. 19, 1982, 96 Stat. 1689; Pub. L. 97–448, title I, § 102(aa), Jan. 12, 1983, 96 Stat. 2369; Pub. L. 98–369, div. A, title I, § 13, July 18, 1984, 98 Stat. 505; Pub. L. 99–514, title II, §§ 201(d)(3), 202, Oct. 22, 1986, 100 Stat. 2139, 2142; Pub. L. 100–647, title I, § 1002(a)(19), (b)(1), Nov. 10, 1988, 102 Stat. 3356, 3357; Pub. L. 101–508, title XI, § 11813(b)(11), Nov. 5, 1990, 104 Stat. 1388–554; Pub. L. 103–66, title XIII, § 13116(a), Aug. 10, 1993, 107 Stat. 432; Pub. L. 104–188, title I, §§ 1111(a), 1702(h)(10), (19), Aug. 20, 1996, 110 Stat. 1758, 1874; Pub. L. 108–27, title II, § 202(a)–(e), May 28, 2003, 117 Stat. 757, 758; Pub. L. 108–357, title II, § 201, title VIII, § 910(a), Oct. 22, 2004, 118 Stat. 1429, 1659; Pub. L. 109–222, title I, § 101, May 17, 2006, 120 Stat. 346; Pub. L. 110–28, title VIII, § 8212(a)–(c), May 25, 2007, 121 Stat. 192; Pub. L. 110–185, title I, § 102(a), Feb. 13, 2008, 122 Stat. 618; Pub. L. 110–343, div. C, title VII, § 711(a), Oct. 3, 2008, 122 Stat. 3928; Pub. L. 111–5, div. B, title I, § 1202(a), Feb. 17, 2009, 123 Stat. 335; Pub. L. 111–147, title II, § 201(a), Mar. 18, 2010, 124 Stat. 77; Pub. L. 111–240, title II, § 2021(a)–(d), Sept. 27, 2010, 124 Stat. 2556, 2558; Pub. L. 111–312, title IV, § 402(a)–(e), title VII, § 737(b)(3), Dec. 17, 2010, 124 Stat. 3306, 3307, 3318; Pub. L. 112–240, title III, § 315(a)–(d), Jan. 2, 2013, 126 Stat. 2330, 2331; Pub. L. 113–295, div. A, title I, § 127(a)–(d), Dec. 19, 2014, 128 Stat. 4017; Pub. L. 114–113, div. Q, title I, § 124(a)–(f), Dec. 18, 2015, 129 Stat. 3053; Pub. L. 115–97, title I, §§ 11002(d)(1)(R), 13101(a)–(c), Dec. 22, 2017, 131 Stat. 2060, 2101, 2102; Pub. L. 115–141, div. U, title IV, § 401(b)(15)(A), (B), Mar. 23, 2018, 132 Stat. 1202; Pub. L. 119–21, title VII, § 70306(a), (b), July 4, 2025, 139 Stat. 197.) | C3: =IFERROR(__xludf.DUMMYFUNCTION("GEMINI(""Summarize IRC §41 in exactly 1 sentence under 20 words. Focus on who qualifies and the credit value. Text: ""&B3)"),"Businesses can immediately deduct the full cost of qualifying equipment and software instead of depreciating it over time.") -> Businesses can immediately deduct the full cost of qualifying equipment and software instead of depreciating it over time. | D3: =IFERROR(__xludf.DUMMYFUNCTION("GEMINI(""List 3-5 industries and 2-3 entity types most affected. Format exactly: Industries: [x,y,z] | Entities: [a,b,c]. Text: ""&B3)"),"Industries: [Motion Picture and Video, Sound Recording, Performing Arts, Agriculture, Transportation] | Entities: [Corporations, Limited Liability Companies, Partnerships]") -> Industries: [Motion Picture and Video, Sound Recording, Performing Arts, Agriculture, Transportation] | Entities: [Corporations, Limited Liability Companies, Partnerships] | E3: =IFERROR(__xludf.DUMMYFUNCTION("GEMINI(""What QuickBooks data fields check if §41 applies? List comma-separated account names or report fields. Text: ""&B3)"),"Fixed Asset Accounts, Purchase Date, Asset Description, Original Cost, Accumulated Depreciation, Section 179/Bonus Depreciation Election, Chart of Accounts (for business type and floor plan financing interest), Vehicle Log (for 280F compliance), Item List"&" (for computer software or media productions)") -> Fixed Asset Accounts, Purchase Date, Asset Description, Original Cost, Accumulated Depreciation, Section 179/Bonus Depreciation Election, Chart of Accounts (for business type and floor plan financing interest), Vehicle Log (for 280F compliance), Item List (for computer software or media productions) | F3: 🚨 Important: Section 179 Expensing Update for [Entity] How this affects you: Great news for [Year]! Based on your [R&D_Spend] in qualifying property investments, your business could be eligible for a significant tax deduction. We estimate your potential credit at [Credit_Estimate]. This incentive allows [Entity] to treat the cost of qualifying section 179 property—like equipment, software, and certain real property improvements—as an immediate expense rather than a capital charge. For the [Year] taxable year, you can deduct up to $2,500,000 of the adjusted basis for assets placed in service this year. ✅ File Form 6765 to elect and claim your specific section 179 deductions ✅ Schedule a CPA review to ensure your property meet "active conduct of trade or business" requirements ✅ Update your QuickBooks tagging for all fixed assets to automate tracking and compliance 📚 Source: IRC Section 179 ⚠️ Disclaimer: This template is for informational purposes only. Tax laws are subject to change and individual circumstances vary. Please consult with a qualified tax professional to confirm eligibility and compliance for your specific entity. | G3: =IFERROR(__xludf.DUMMYFUNCTION("GEMINI(""Explain in 1 sentence how §179 impacts ratios like Effective Tax Rate or R&D Intensity. For a non-accountant CFO. Text: ""&B3)"),"IRC Section 179 provides an immediate deduction for equipment and software costs, which lowers taxable income and reduces your effective tax rate in the year these assets are placed in service.") -> IRC Section 179 provides an immediate deduction for equipment and software costs, which lowers taxable income and reduces your effective tax rate in the year these assets are placed in service.
A4: §41 | B4: §41(a): A credit is allowed against tax for increasing research activities. Qualified research expenses include wages, supplies, and contract research. Credit rate: 20% of current QREs over base amount, or 14% of QREs for alternative simplified credit. Startups may elect to apply up to $500K against payroll tax. | C4: =IFERROR(__xludf.DUMMYFUNCTION("GEMINI(""Summarize IRC §41 in exactly 1 sentence under 20 words. Focus on who qualifies and the credit value. Text: ""&B4)"),"Businesses and startups qualify for a tax credit worth 14% to 20% of qualified research expenses.") -> Businesses and startups qualify for a tax credit worth 14% to 20% of qualified research expenses. | D4: =IFERROR(__xludf.DUMMYFUNCTION("GEMINI(""List 3-5 industries and 2-3 entity types most affected. Format exactly: Industries: [x,y,z] | Entities: [a,b,c]. Text: ""&B4)"),"Industries: [Technology, Life Sciences, Manufacturing, Biotechnology, Aerospace] | Entities: [Corporations, Partnerships, Limited Liability Companies]") -> Industries: [Technology, Life Sciences, Manufacturing, Biotechnology, Aerospace] | Entities: [Corporations, Partnerships, Limited Liability Companies] | E4: =IFERROR(__xludf.DUMMYFUNCTION("GEMINI(""What QuickBooks data fields check if §41 applies? List comma-separated account names or report fields. Text: ""&B4)"),"Payroll Expenses (Wages), Supplies Expense, Contractor/Consultant Fees, R&D Expense (Class/Account), Employee Time Tracking/Timesheets, Project Name, Project Description, Purchase Orders, Vendor Invoices, Form 941 (Payroll Tax), Gross Receipts (Sales)") -> Payroll Expenses (Wages), Supplies Expense, Contractor/Consultant Fees, R&D Expense (Class/Account), Employee Time Tracking/Timesheets, Project Name, Project Description, Purchase Orders, Vendor Invoices, Form 941 (Payroll Tax), Gross Receipts (Sales) | F4: 🚨 Important: Research & Development Tax Credit for [Entity] How this affects you: Great news for [Year]\! Based on your [R&D_Spend] in qualified research expenses, your business could be eligible for a significant tax credit. We estimate your potential credit at [Credit_Estimate]. This incentive is designed to reward your innovation by allowing you to claim a credit for wages, supplies, and contract research, helping you reinvest in your company's growth. ✅ Ensure all qualified expenses are properly documented for Form 6765 ✅ Schedule a CPA review to verify your eligibility and maximize your credit ✅ Confirm that all R\&D-related transactions are correctly tagged in QuickBooks 📚 Source: IRC Section 41 ⚠️ Disclaimer: This template is for informational purposes only. Tax laws are subject to change and individual circumstances vary. Please consult with a qualified tax professional to confirm eligibility and compliance for your specific entity. | G4: =IFERROR(__xludf.DUMMYFUNCTION("GEMINI(""Explain in 1 sentence how §41 impacts ratios like Effective Tax Rate or R&D Intensity. For a non-accountant CFO. Text: ""&B4)"),"IRC Section 41 provides a dollar-for-dollar credit that directly reduces your effective tax rate while incentivizing a higher R&D intensity by lowering the after-tax cost of innovation.") -> IRC Section 41 provides a dollar-for-dollar credit that directly reduces your effective tax rate while incentivizing a higher R&D intensity by lowering the after-tax cost of innovation.
A5: §3121 | B5: Defines wages for FICA tax purposes. For 2026, the Social Security wage base limit is $184,500. Wages above this are exempt from the 6.2% Social Security tax. | C5: =IFERROR(__xludf.DUMMYFUNCTION("GEMINI(""Summarize IRC §3121 in exactly 1 sentence under 20 words. Focus on the FICA wage base limit and who it affects. Text: ""&B5)"),"IRC §3121 limits FICA taxes to the first $184,500 of an employee's wages in 2026.") -> IRC §3121 limits FICA taxes to the first $184,500 of an employee's wages in 2026. | D5: =IFERROR(__xludf.DUMMYFUNCTION("GEMINI(""List 3-5 industries and 2-3 entity types most affected. Format exactly: Industries: [x,y,z] | Entities: [a,b,c]. Text: ""&B5)"),"Industries: [Technology, Professional Services, Finance, Healthcare, Manufacturing] | Entities: [Corporations, Limited Liability Companies, Partnerships]") -> Industries: [Technology, Professional Services, Finance, Healthcare, Manufacturing] | Entities: [Corporations, Limited Liability Companies, Partnerships] | E5: =IFERROR(__xludf.DUMMYFUNCTION("GEMINI(""What QuickBooks data fields check if §3121 applies? List comma-separated payroll fields or reports. Text: ""&B5)"),"Payroll Expenses: Wages, Payroll Expenses: Taxes, Payroll Liabilities: Federal Taxes (941/944), Employee Profile (Tax Withholding), Payroll Item List, Payroll Summary Report, Payroll Tax and Wage Summary Report, Taxable Wage Audit Report, W-2 Forms") -> Payroll Expenses: Wages, Payroll Expenses: Taxes, Payroll Liabilities: Federal Taxes (941/944), Employee Profile (Tax Withholding), Payroll Item List, Payroll Summary Report, Payroll Tax and Wage Summary Report, Taxable Wage Audit Report, W-2 Forms | F5: 🚨 Important: FICA Wage Base Limit Update for [Entity] How this affects you: For the 2026 tax year, the Social Security wage base is set at [Wage_Base]. This means that for your [Employee_Count] employees, any wages paid above this threshold are exempt from the 6.2% Social Security tax. Once an employee's year-to-date earnings surpass this limit, you should stop withholding the 6.2% employee portion and stop paying the 6.2% employer portion for the remainder of the year. ✅ Perform a payroll review to identify employees approaching the [Wage_Base] limit ✅ Verify that year-to-end W-2 wage reporting correctly reflects the Social Security cap ✅ Ensure all high-earner payroll items are correctly tagged in QuickBooks for accurate tax tracking 📚 Source: IRC Section 3121 ⚠️ Disclaimer: This template is for informational purposes only. Tax laws are subject to change and individual circumstances vary. Please consult with a qualified tax professional to confirm eligibility and compliance for your specific entity. | G5: =IFERROR(__xludf.DUMMYFUNCTION("GEMINI(""Explain in 1 sentence how §3121 impacts cash flow or payroll tax ratios. For a non-accountant CFO. Text: ""&B5)"),"IRC Section 3121 improves cash flow and lowers your effective payroll tax ratio by exempting employee wages above $184,500 from the 6.2% Social Security tax.") -> IRC Section 3121 improves cash flow and lowers your effective payroll tax ratio by exempting employee wages above $184,500 from the 6.2% Social Security tax.
B6: (g)Agricultural labor For purposes of this chapter, the term “agricultural labor” includes all service performed— (1)on a farm, in the employ of any person, in connection with cultivating the soil, or in connection with raising or harvesting any agricultural or horticultural commodity, including the raising, shearing, feeding, caring for, training, and management of livestock, bees, poultry, and fur-bearing animals and wildlife; (2)in the employ of the owner or tenant or other operator of a farm, in connection with the operation, management, conservation, improvement, or maintenance of such farm and its tools and equipment, or in salvaging timber or clearing land of brush and other debris left by a hurricane, if the major part of such service is performed on a farm; (3)in connection with the production or harvesting of any commodity defined as an agricultural commodity in section 15(g) of the Agricultural Marketing Act, as amended (12 U.S.C. 1141j), or in connection with the ginning of cotton, or in connection with the operation or maintenance of ditches, canals, reservoirs, or waterways, not owned or operated for profit, used exclusively for supplying and storing water for farming purposes; (4) (A)in the employ of the operator of a farm in handling, planting, drying, packing, packaging, processing, freezing, grading, storing, or delivering to storage or to market or to a carrier for transportation to market, in its unmanufactured state, any agricultural or horticultural commodity; but only if such operator produced more than one-half of the commodity with respect to which such service is performed; (B)in the employ of a group of operators of farms (other than a cooperative organization) in the performance of service described in subparagraph (A), but only if such operators produced all of the commodity with respect to which such service is performed. For purposes of this subparagraph, any unincorporated group of operators shall be deemed a cooperative organization if the number of operators comprising such group is more than 20 at any time during the calendar year in which such service is performed; (C)the provisions of subparagraphs (A) and (B) shall not be deemed to be applicable with respect to service performed in connection with commercial canning or commercial freezing or in connection with any agricultural or horticultural commodity after its delivery to a terminal market for distribution for consumption; or (5)on a farm operated for profit if such service is not in the course of the employer’s trade or business. As used in this subsection, the term “farm” includes stock, dairy, poultry, fruit, fur-bearing animal, and truck farms, plantations, ranches, nurseries, ranges, greenhouses or other similar structures used primarily for the raising of agricultural or horticultural commodities, and orchards. (h)American employer For purposes of this chapter, the term “American employer” means an employer which is— (1)the United States or any instrumentality thereof, (2)an individual who is a resident of the United States, (3)a partnership, if two-thirds or more of the partners are residents of the United States, (4)a trust, if all of the trustees are residents of the United States, or (5)a corporation organized under the laws of the United States or of any State. (i)Computation of wages in certain cases (1)Domestic service For purposes of this chapter, in the case of domestic service described in subsection (a)(7)(B), any payment of cash remuneration for such service which is more or less than a whole-dollar amount shall, under such conditions and to such extent as may be prescribed by regulations made under this chapter, be computed to the nearest dollar. For the purpose of the computation to the nearest dollar, the payment of a fractional part of a dollar shall be disregarded unless it amounts to one-half dollar or more, in which case it shall be increased to $1. The amount of any payment of cash remuneration so computed to the nearest dollar shall, in lieu of the amount actually paid, be deemed to constitute the amount of cash remuneration for purposes of subsection (a)(7)(B). (2)Service in the uniformed services For purposes of this chapter, in the case of an individual performing service, as a member of a uniformed service, to which the provisions of subsection (m)(1) are applicable, the term “wages” shall, subject to the provisions of subsection (a)(1) of this section, include as such individual’s remuneration for such service only (A) his basic pay as described in chapter 3 and section 1009 of title 37, United States Code, in the case of an individual performing service to which subparagraph (A) of such subsection (m)(1) applies, or (B) his compensation for such service as determined under section 206(a) of title 37, United States Code, in the case of an individual performing service to which subparagraph (B) of such subsection (m)(1) applies. (3)Peace Corps volunteer service For purposes of this chapter, in the case of an individual performing service, as a volunteer or volunteer leader within the meaning of the Peace Corps Act, to which the provisions of section 3121(p) are applicable, the term “wages” shall, subject to the provisions of subsection (a)(1) of this section, include as such individual’s remuneration for such service only amounts paid pursuant to section 5(c) or 6(1) of the Peace Corps Act. (4)Service performed by certain members of religious orders For purposes of this chapter, in any case where an individual is a member of a religious order (as defined in subsection (r)(2)) performing service in the exercise of duties required by such order, and an election of coverage under subsection (r) is in effect with respect to such order or with respect to the autonomous subdivision thereof to which such member belongs, the term “wages” shall, subject to the provisions of subsection (a)(1), include as such individual’s remuneration for such service the fair market value of any board, lodging, clothing, and other perquisites furnished to such member by such order or subdivision thereof or by any other person or organization pursuant to an agreement with such order or subdivision, except that the amount included as such individual’s remuneration under this paragraph shall not be less than $100 a month. (5)Service performed by certain retired justices and judges For purposes of this chapter, in the case of an individual performing service under the provisions of section 294 of title 28, United States Code (relating to assignment of retired justices and judges to active duty), the term “wages” shall not include any payment under section 371(b) of such title 28 which is received during the period of such service. (j)Covered transportation service For purposes of this chapter— (1)Existing transportation systems—General rule Except as provided in paragraph (2), all service performed in the employ of a State or political subdivision in connection with its operation of a public transportation system shall constitute covered transportation service if any part of the transportation system was acquired from private ownership after 1936 and prior to 1951. (2)Existing transportation systems—Cases in which no transportation employees, or only certain employees, are covered Service performed in the employ of a State or political subdivision in connection with the operation of its public transportation system shall not constitute covered transportation service if— (A)any part of the transportation system was acquired from private ownership after 1936 and prior to 1951, and substantially all service in connection with the operation of the transportation system was, on December 31, 1950, covered under a general retirement system providing benefits which, by reason of a provision of the State constitution dealing specifically with retirement systems of the State or political subdivisions thereof, cannot be diminished or impaired; or (B)no part of the transportation system operated by the State or political subdivision on December 31, 1950, was acquired from private ownership after 1936 and prior to 1951; except that if such State or political subdivision makes an acquisition after 1950 from private ownership of any part of its transportation system, then, in the case of any employee who— (C)became an employee of such State or political subdivision in connection with and at the time of its acquisition after 1950 of such part, and (D)prior to such acquisition rendered service in employment (including as employment service covered by an agreement under section 218 of the Social Security Act) in connection with the operation of such part of the transportation system acquired by the State or political subdivision, the service of such employee in connection with the operation of the transportation system shall constitute covered transportation service, commencing with the first day of the third calendar quarter following the calendar quarter in which the acquisition of such part took place, unless on such first day such service of such employee is covered by a general retirement system which does not, with respect to such employee, contain special provisions applicable only to employees described in subparagraph (C). (3)Transportation systems acquired after 1950 All service performed in the employ of a State or political subdivision thereof in connection with its operation of a public transportation system shall constitute covered transportation service if the transportation system was not operated by the State or political subdivision prior to 1951 and, at the time of its first acquisition (after 1950) from private ownership of any part of its transportation system, the State or political subdivision did not have a general retirement system covering substantially all service performed in connection with the operation of the transportation system. (4)Definitions For purposes of this subsection— (A)The term “general retirement system” means any pension, annuity, retirement, or similar fund or system established by a State or by a political subdivision thereof for employees of the State, political subdivision, or both; but such term shall not include such a fund or system which covers only service performed in positions connected with the operation of its public transportation system. (B)A transportation system or a part thereof shall be considered to have been acquired by a State or political subdivision from private ownership if prior to the acquisition service performed by employees in connection with the operation of the system or part thereof acquired constituted employment under this chapter or subchapter A of chapter 9 of the Internal Revenue Code of 1939 or was covered by an agreement made pursuant to section 218 of the Social Security Act and some of such employees became employees of the State or political subdivision in connection with and at the time of such acquisition. (C)The term “political subdivision” includes an instrumentality of— (i)a State, (ii)one or more political subdivisions of a State, or (iii)a State and one or more of its political subdivisions. [(k)Repealed. Pub. L. 98–21, title I, § 102(b)(2), Apr. 20, 1983, 97 Stat. 71] (l)Agreements entered into by American employers with respect to foreign affiliates (1)Agreement with respect to certain employees of foreign affiliate The Secretary shall, at the American employer’s request, enter into an agreement (in such manner and form as may be prescribed by the Secretary) with any American employer (as defined in subsection (h)) who desires to have the insurance system established by title II of the Social Security Act extended to service performed outside the United States in the employ of any 1 or more of such employer’s foreign affiliates (as defined in paragraph (6)) by all employees who are citizens or residents of the United States, except that the agreement shall not apply to any service performed by, or remuneration paid to, an employee if such service or remuneration would be excluded from the term “employment” or “wages”, as defined in this section, had the service been performed in the United States. Such agreement may be amended at any time so as to be made applicable, in the same manner and under the same conditions, with respect to any other foreign affiliate of such American employer. Such agreement shall be applicable with respect to citizens or residents of the United States who, on or after the effective date of the agreement, are employees of and perform services outside the United States for any foreign affiliate specified in the agreement. Such agreement shall provide— (A)that the American employer shall pay to the Secretary, at such time or times as the Secretary may by regulations prescribe, amounts equivalent to the sum of the taxes which would be imposed by sections 3101 and 3111 (including amounts equivalent to the interest, additions to the taxes, additional amounts, and penalties which would be applicable) with respect to the remuneration which would be wages if the services covered by the agreement constituted employment as defined in this section; and (B)that the American employer will comply with such regulations relating to payments and reports as the Secretary may prescribe to carry out the purposes of this subsection. (2)Effective period of agreement An agreement entered into pursuant to paragraph (1) shall be in effect for the period beginning with the first day of the calendar quarter in which such agreement is entered into or the first day of the succeeding calendar quarter, as may be specified in the agreement; except that in case such agreement is amended to include the services performed for any other affiliate and such amendment is executed after the first month following the first calendar quarter for which the agreement is in effect, the agreement shall be in effect with respect to service performed for such other affiliate only after the calendar quarter in which such amendment is executed. Notwithstanding any other provision of this subsection, the period for which any such agreement is effective with respect to any foreign entity shall terminate at the end of any calendar quarter in which the foreign entity, at any time in such quarter, ceases to be a foreign affiliate as defined in paragraph (6). (3)No termination of agreement No agreement under this subsection may be terminated, either in its entirety or with respect to any foreign affiliate, on or after June 15, 1989. (4)Deposits in trust funds For purposes of section 201 of the Social Security Act, relating to appropriations to the Federal Old-Age and Survivors Insurance Trust Fund and the Federal Disability Insurance Trust Fund, such remuneration— (A)paid for services covered by an agreement entered into pursuant to paragraph (1) as would be wages if the services constituted employment, and (B)as is reported to the Secretary pursuant to the provisions of such agreement or of the regulations issued under this subsection, shall be considered wages subject to the taxes imposed by this chapter. (5)Overpayments and underpayments (A)If more or less than the correct amount due under an agreement entered into pursuant to this subsection is paid with respect to any payment of remuneration, proper adjustments with respect to the amounts due under such agreement shall be made, without interest, in such manner and at such times as may be required by regulations prescribed by the Secretary. (B)If an overpayment cannot be adjusted under subparagraph (A), the amount thereof shall be paid by the Secretary, through the Fiscal Service of the Treasury Department, but only if a claim for such overpayment is filed with the Secretary within two years from the time such overpayment was made. (6)Foreign affiliate defined For purposes of this subsection and section 210(a) of the Social Security Act— (A)In general A foreign affiliate of an American employer is any foreign entity in which such American employer has not less than a 10-percent interest. (B)Determination of 10-percent interest For purposes of subparagraph (A), an American employer has a 10-percent interest in any entity if such employer has such an interest directly (or through one or more entities)— (i)in the case of a corporation, in the voting stock thereof, and (ii)in the case of any other entity, in the profits thereof. (7)American employer as separate entity Each American employer which enters into an agreement pursuant to paragraph (1) of this subsection shall, for purposes of this subsection and section 6413(c)(2)(C), relating to special refunds in the case of employees of certain foreign entities, be considered an employer in its capacity as a party to such agreement separate and distinct from its identity as a person employing individuals on its own account. (8)Regulations Regulations of the Secretary to carry out the purposes of this subsection shall be designed to make the requirements imposed on American employers with respect to services covered by an agreement entered into pursuant to this subsection the same, so far as practicable, as those imposed upon employers pursuant to this title with respect to the taxes imposed by this chapter. (m)Service in the uniformed services For purposes of this chapter— (1)Inclusion of service The term “employment” shall, notwithstanding the provisions of subsection (b) of this section, include— (A)service performed by an individual as a member of a uniformed service on active duty, but such term shall not include any such service which is performed while on leave without pay, and (B)service performed by an individual as a member of a uniformed service on inactive duty training. (2)Active duty The term “active duty” means “active duty” as described in paragraph (21) of section 101 of title 38, United States Code, except that it shall also include “active duty for training” as described in paragraph (22) of such section. (3)Inactive duty training The term “inactive duty training” means “inactive duty training” as described in paragraph (23) of such section 101. (n)Member of a uniformed service For purposes of this chapter, the term “member of a uniformed service” means any person appointed, enlisted, or inducted in a component of the Army, Navy, Air Force, Marine Corps, or Coast Guard (including a reserve component as defined in section 101(27) of title 38, United States Code), or in one of those services without specification of component, or as a commissioned officer of the Coast and Geodetic Survey, the National Oceanic and Atmospheric Administration Corps, or the Regular or Reserve Corps [2] of the Public Health Service, and any person serving in the Army or Air Force under call or conscription. The term includes— (1)a retired member of any of those services; (2)a member of the Fleet Reserve or Fleet Marine Corps Reserve; (3)a cadet at the United States Military Academy, a midshipman at the United States Naval Academy, and a cadet at the United States Coast Guard Academy or United States Air Force Academy; (4)a member of the Reserve Officers’ Training Corps, the Naval Reserve Officers’ Training Corps, or the Air Force Reserve Officers’ Training Corps, when ordered to annual training duty for fourteen days or more, and while performing authorized travel to and from that duty; and (5)any person while en route to or from, or at, a place for final acceptance or for entry upon active duty in the military, naval, or air service— (A)who has been provisionally accepted for such duty; or (B)who, under the Military Selective Service Act, has been selected for active military, naval, or air service; and has been ordered or directed to proceed to such place. The term does not include a temporary member of the Coast Guard Reserve. (o)Crew leader For purposes of this chapter, the term “crew leader” means an individual who furnishes individuals to perform agricultural labor for another person, if such individual pays (either on his own behalf or on behalf of such person) the individuals so furnished by him for the agricultural labor performed by them and if such individual has not entered into a written agreement with such person whereby such individual has been designated as an employee of such person; and such individuals furnished by the crew leader to perform agricultural labor for another person shall be deemed to be the employees of such crew leader. For purposes of this chapter and chapter 2, a crew leader shall, with respect to service performed in furnishing individuals to perform agricultural labor for another person and service performed as a member of the crew, be deemed not to be an employee of such other person. (p)Peace Corps volunteer service For purposes of this chapter, the term “employment” shall, notwithstanding the provisions of subsection (b) of this section, include service performed by an individual as a volunteer or volunteer leader within the meaning of the Peace Corps Act. (q)Tips included for both employee and employer taxes For purposes of this chapter, tips received by an employee in the course of his employment shall be considered remuneration for such employment (and deemed to have been paid by the employer for purposes of subsections (a) and (b) of section 3111). Such remuneration shall be deemed to be paid at the time a written statement including such tips is furnished to the employer pursuant to section 6053(a) or (if no statement including such tips is so furnished) at the time received; except that, in determining the employer’s liability in connection with the taxes imposed by section 3111 with respect to such tips in any case where no statement including such tips was so furnished (or to the extent that the statement so furnished was inaccurate or incomplete), such remuneration shall be deemed for purposes of subtitle F to be paid on the date on which notice and demand for such taxes is made to the employer by the Secretary. (r)Election of coverage by religious orders (1)Certificate of election by order A religious order whose members are required to take a vow of poverty, or any autonomous subdivision of such order, may file a certificate (in such form and manner, and with such official, as may be prescribed by regulations under this chapter) electing to have the insurance system established by title II of the Social Security Act extended to services performed by its members in the exercise of duties required by such order or such subdivision thereof. Such certificate of election shall provide that— (A)such election of coverage by such order or subdivision shall be irrevocable; (B)such election shall apply to all current and future members of such order, or in the case of a subdivision thereof to all current and future members of such order who belong to such subdivision; (C)all services performed by a member of such an order or subdivision in the exercise of duties required by such order or subdivision shall be deemed to have been performed by such member as an employee of such order or subdivision; and (D)the wages of each member, upon which such order or subdivision shall pay the taxes imposed by sections 3101 and 3111, will be determined as provided in subsection (i)(4). (2)Definition of member For purposes of this subsection, a member of a religious order means any individual who is subject to a vow of poverty as a member of such order and who performs tasks usually required (and to the extent usually required) of an active member of such order and who is not considered retired because of old age or total disability. (3)Effective date for election (A)A certificate of election of coverage shall be in effect, for purposes of subsection (b)(8) and for purposes of section 210(a)(8) of the Social Security Act, for the period beginning with whichever of the following may be designated by the order or subdivision thereof: (i)the first day of the calendar quarter in which the certificate is filed, (ii)the first day of the calendar quarter succeeding such quarter, or (iii)the first day of any calendar quarter preceding the calendar quarter in which the certificate is filed, except that such date may not be earlier than the first day of the twentieth calendar quarter preceding the quarter in which such certificate is filed. Whenever a date is designated under clause (iii), the election shall apply to services performed before the quarter in which the certificate is filed only if the member performing such services was a member at the time such services were performed and is living on the first day of the quarter in which such certificate is filed. (B)If a certificate of election filed pursuant to this subsection is effective for one or more calendar quarters prior to the quarter in which such certificate is filed, then— (i)for purposes of computing interest and for purposes of section 6651 (relating to addition to tax for failure to file tax return), the due date for the return and payment of the tax for such prior calendar quarters resulting from the filing of such certificate shall be the last day of the calendar month following the calendar quarter in which the certificate is filed; and (ii)the statutory period for the assessment of such tax shall not expire before the expiration of 3 years from such due date. [(4)Repealed. Pub. L. 98–21, title I, § 102(b)(3)(B), Apr. 20, 1983, 97 Stat. 71] (s)Concurrent employment by two or more employers For purposes of sections 3102, 3111, and 3121(a)(1), if two or more related corporations concurrently employ the same individual and compensate such individual through a common paymaster which is one of such corporations, each such corporation shall be considered to have paid as remuneration to such individual only the amounts actually disbursed by it to such individual and shall not be considered to have paid as remuneration to such individual amounts actually disbursed to such individual by another of such corporations. [(t)Repealed. Pub. L. 100–203, title IX, § 9006(b)(2), Dec. 22, 1987, 101 Stat. 1330–289] (u)Application of hospital insurance tax to Federal, State, and local employment (1)Federal employment For purposes of the taxes imposed by sections 3101(b) and 3111(b), subsection (b) shall be applied without regard to paragraph (5) thereof. (2)State and local employment For purposes of the taxes imposed by sections 3101(b) and 3111(b)— (A)In general Except as provided in subparagraphs (B) and (C), subsection (b) shall be applied without regard to paragraph (7) thereof. (B)Exception for certain services Service shall not be treated as employment by reason of subparagraph (A) if— (i)the service is included under an agreement under section 218 of the Social Security Act, or (ii)the service is performed— (I)by an individual who is employed by a State or political subdivision thereof to relieve him from unemployment, (II)in a hospital, home, or other institution by a patient or inmate thereof as an employee of a State or political subdivision thereof or of the District of Columbia, (III)by an individual, as an employee of a State or political subdivision thereof or of the District of Columbia, serving on a temporary basis in case of fire, storm, snow, earthquake, flood or other similar emergency, (IV)by any individual as an employee included under section 5351(2) of title 5, United States Code (relating to certain interns, student nurses, and other student employees of hospitals of the District of Columbia Government), other than as a medical or dental intern or a medical or dental resident in training, (V)by an election official or election worker if the remuneration paid in a calendar year for such service is less than $1,000 with respect to service performed during any calendar year commencing on or after January 1, 1995, ending on or before December 31, 1999, and the adjusted amount determined under section 218(c)(8)(B) of the Social Security Act for any calendar year commencing on or after January 1, 2000, with respect to service performed during such calendar year, or (VI)by an individual in a position described in section 1402(c)(2)(E). As used in this subparagraph, the terms “State” and “political subdivision” have the meanings given those terms in section 218(b) of the Social Security Act. (C)Exception for current employment which continues Service performed for an employer shall not be treated as employment by reason of subparagraph (A) if— (i)such service would be excluded from the term “employment” for purposes of this chapter if subparagraph (A) did not apply; (ii)such service is performed by an individual— (I)who was performing substantial and regular service for remuneration for that employer before April 1, 1986, (II)who is a bona fide employee of that employer on March 31, 1986, and (III)whose employment relationship with that employer was not entered into for purposes of meeting the requirements of this subparagraph; and (iii)the employment relationship with that employer has not been terminated after March 31, 1986. (D)Treatment of agencies and instrumentalities For purposes of subparagraph (C), under regulations— (i)All agencies and instrumentalities of a State (as defined in section 218(b) of the Social Security Act) or of the District of Columbia shall be treated as a single employer. (ii)All agencies and instrumentalities of a political subdivision of a State (as so defined) shall be treated as a single employer and shall not be treated as described in clause (i). (3)Medicare qualified government employment For purposes of this chapter, the term “medicare qualified government employment” means service which— (A)is employment (as defined in subsection (b)) with the application of paragraphs (1) and (2), but (B)would not be employment (as so defined) without the application of such paragraphs. (v)Treatment of certain deferred compensation and salary reduction arrangements (1)Certain employer contributions treated as wages Nothing in any paragraph of subsection (a) (other than paragraph (1)) shall exclude from the term “wages”— (A)any employer contribution under a qualified cash or deferred arrangement (as defined in section 401(k)) to the extent not included in gross income by reason of section 402(e)(3) or consisting of designated Roth contributions (as defined in section 402A(c)), or (B)any amount treated as an employer contribution under section 414(h)(2) where the pickup referred to in such section is pursuant to a salary reduction agreement (whether evidenced by a written instrument or otherwise). (2)Treatment of certain nonqualified deferred compensation plans (A)In general Any amount deferred under a nonqualified deferred compensation plan shall be taken into account for purposes of this chapter as of the later of— (i)when the services are performed, or (ii)when there is no substantial risk of forfeiture of the rights to such amount. The preceding sentence shall not apply to any excess parachute payment (as defined in section 280G(b)) or to any specified stock compensation (as defined in section 4985) on which tax is imposed by section 4985. (B)Taxed only once Any amount taken into account as wages by reason of subparagraph (A) (and the income attributable thereto) shall not thereafter be treated as wages for purposes of this chapter. (C)Nonqualified deferred compensation plan For purposes of this paragraph, the term “nonqualified deferred compensation plan” means any plan or other arrangement for deferral of compensation other than a plan described in subsection (a)(5). (3)Exempt governmental deferred compensation plan For purposes of subsection (a)(5), the term “exempt governmental deferred compensation plan” means any plan providing for deferral of compensation established and maintained for its employees by the United States, by a State or political subdivision thereof, or by an agency or instrumentality of any of the foregoing. Such term shall not include— (A)any plan to which section 83, 402(b), 403(c), 457(a), or 457(f)(1) applies, (B)any annuity contract described in section 403(b), and (C)the Thrift Savings Fund (within the meaning of subchapter III of chapter 84 of title 5, United States Code). (w)Exemption of churches and qualified church-controlled organizations (1)General rule Any church or qualified church-controlled organization (as defined in paragraph (3)) may make an election within the time period described in paragraph (2), in accordance with such procedures as the Secretary determines to be appropriate, that services performed in the employ of such church or organization shall be excluded from employment for purposes of title II of the Social Security Act and this chapter. An election may be made under this subsection only if the church or qualified church-controlled organization states that such church or organization is opposed for religious reasons to the payment of the tax imposed under section 3111. (2)Timing and duration of election An election under this subsection must be made prior to the first date, more than 90 days after July 18, 1984, on which a quarterly employment tax return for the tax imposed under section 3111 is due, or would be due but for the election, from such church or organization. An election under this subsection shall apply to current and future employees, and shall apply to service performed after December 31, 1983. The election may be revoked by the church or organization under regulations prescribed by the Secretary. The election shall be revoked by the Secretary if such church or organization fails to furnish the information required under section 6051 to the Secretary for a period of 2 years or more with respect to remuneration paid for such services by such church or organization, and, upon request by the Secretary, fails to furnish all such previously unfurnished information for the period covered by the election. Any revocation under the preceding sentence shall apply retroactively to the beginning of the 2-year period for which the information was not furnished. (3)Definitions (A)For purposes of this subsection, the term “church” means a church, a convention or association of churches, or an elementary or secondary school which is controlled, operated, or principally supported by a church or by a convention or association of churches. (B)For purposes of this subsection, the term “qualified church-controlled organization” means any church-controlled tax-exempt organization described in section 501(c)(3), other than an organization which— (i)offers goods, services, or facilities for sale, other than on an incidental basis, to the general public, other than goods, services, or facilities which are sold at a nominal charge which is substantially less than the cost of providing such goods, services, or facilities; and (ii)normally receives more than 25 percent of its support from either (I) governmental sources, or (II) receipts from admissions, sales of merchandise, performance of services, or furnishing of facilities, in activities which are not unrelated trades or businesses, or both. (x)Applicable dollar threshold For purposes of subsection (a)(7)(B), the term “applicable dollar threshold” means $1,000. In the case of calendar years after 1995, the Commissioner of Social Security shall adjust such $1,000 amount at the same time and in the same manner as under section 215(a)(1)(B)(ii) of the Social Security Act with respect to the amounts referred to in section 215(a)(1)(B)(i) of such Act, except that, for purposes of this paragraph, 1993 shall be substituted for the calendar year referred to in section 215(a)(1)(B)(ii)(II) of such Act. If any amount as adjusted under the preceding sentence is not a multiple of $100, such amount shall be rounded to the next lowest multiple of $100. (y)Service in the employ of international organizations by certain transferred Federal employees (1)In general For purposes of this chapter, service performed in the employ of an international organization by an individual pursuant to a transfer of such individual to such international organization pursuant to section 3582 of title 5, United States Code, shall constitute “employment” if— (A)immediately before such transfer, such individual performed service with a Federal agency which constituted “employment” under subsection (b) for purposes of the taxes imposed by sections 3101(a) and 3111(a), and (B)such individual would be entitled, upon separation from such international organization and proper application, to reemployment with such Federal agency under such section 3582. (2)Definitions For purposes of this subsection— (A)Federal agency The term “Federal agency” means an agency, as defined in section 3581(1) of title 5, United States Code. (B)International organization The term “international organization” has the meaning provided such term by section 3581(3) of title 5, United States Code. (z)Treatment of certain foreign persons as American employers (1)In general If any employee of a foreign person is performing services in connection with a contract between the United States Government (or any instrumentality thereof) and any member of any domestically controlled group of entities which includes such foreign person, such foreign person shall be treated for purposes of this chapter as an American employer with respect to such services performed by such employee. (2)Domestically controlled group of entities For purposes of this subsection— (A)In general The term “domestically controlled group of entities” means a controlled group of entities the common parent of which is a domestic corporation. (B)Controlled group of entities The term “controlled group of entities” means a controlled group of corporations as defined in section 1563(a)(1), except that— (i)“more than 50 percent” shall be substituted for “at least 80 percent” each place it appears therein, and (ii)the determination shall be made without regard to subsections (a)(4) and (b)(2) of section 1563. A partnership or any other entity (other than a corporation) shall be treated as a member of a controlled group of entities if such entity is controlled (within the meaning of section 954(d)(3)) by members of such group (including any entity treated as a member of such group by reason of this sentence). (3)Liability of common parent In the case of a foreign person who is a member of any domestically controlled group of entities, the common parent of such group shall be jointly and severally liable for any tax under this chapter for which such foreign person is liable by reason of this subsection, and for any penalty imposed on such person by this title with respect to any failure to pay such tax or to file any return or statement with respect to such tax or wages subject to such tax. No deduction shall be allowed under this title for any liability imposed by the preceding sentence. (4)Provisions preventing double taxation (A)Agreements Paragraph (1) shall not apply to any services which are covered by an agreement under subsection (l). (B)Equivalent foreign taxation Paragraph (1) shall not apply to any services if the employer establishes to the satisfaction of the Secretary that the remuneration paid by such employer for such services is subject to a tax imposed by a foreign country which is substantially equivalent to the taxes imposed by this chapter. (5)Cross reference For relief from taxes in cases covered by certain international agreements, see sections 3101(c) and 3111(c). (Aug. 16, 1954, ch. 736, 68A Stat. 417; Sept. 1, 1954, ch. 1206, title II, §§ 204(a), (b), 205(a)–(e), 206(a), 207, 209, 68 Stat. 1091–1094; Aug. 1, 1956, ch. 836, title I, §§ 103(j), 121(d), title II, §§ 201(b)–(d), (e)(1), (h)(1), (2), (j)–(l), 70 Stat. 824, 839–841, 843; Aug. 1, 1956, ch. 837, title IV, §§ 410, 411(a), 70 Stat. 878; Pub. L. 85–840, title IV, §§ 402(b), 404(a), 405(a), (b), Aug. 28, 1958, 72 Stat. 1042, 1044–1046; Pub. L. 85–866, title I, § 69, Sept. 2, 1958, 72 Stat. 1659; Pub. L. 86–70, § 22(a), June 25, 1959, 73 Stat. 146; Pub. L. 86–168, title I, § 104(h), title II, § 202(a), Aug. 18, 1959, 73 Stat. 387, 389; Pub. L. 86–624, § 18(c), July 12, 1960, 74 Stat. 416; Pub. L. 86–778, title I, §§ 103(n)–(p), 104(b), 105(a), Sept. 13, 1960, 74 Stat. 938, 939, 942; Pub. L. 87–256, § 110(e)(1), Sept. 21, 1961, 75 Stat. 536; Pub. L. 87–293, title II, § 202(a)(1), (2), Sept. 22, 1961, 75 Stat. 626; Pub. L. 88–272, title II, § 220(c)(2), Feb. 26, 1964, 78 Stat. 62; Pub. L. 88–650, § 4(b), Oct. 13, 1964, 78 Stat. 1077; Pub. L. 89–97, title III, §§ 311(b)(4), (5), 313(c)(3), (4), 316(a)(1), (b), 317(b), 320(b)(2), July 30, 1965, 79 Stat. 381, 383, 386, 388, 393; Pub. L. 90–248, title I, §§ 108(b)(2), 123(b), title IV, § 403(i), title V, § 504(a), Jan. 2, 1968, 81 Stat. 835, 845, 932, 934; Pub. L. 91–172, title IX, § 943(c)(1)–(3), Dec. 30, 1969, 83 Stat. 728; Pub. L. 92–5, title II, § 203(b)(2), Mar. 17, 1971, 85 Stat. 11; Pub. L. 92–336, title II, § 203(b)(2), July 1, 1972, 86 Stat. 419; Pub. L. 92–603, title I, §§ 104(i), 122(b), 123(a)(2), (b), (c)(2), 128(b), 129(a)(2), 138(b), Oct. 30, 1972, 86 Stat. 1341, 1354, 1356, 1358, 1359, 1365; Pub. L. 93–66, title II, § 203(b)(2), (d), July 9, 1973, 87 Stat. 153; Pub. L. 93–233, § 5(b)(2), (d), Dec. 31, 1973, 87 Stat. 954; Pub. L. 94–455, title XII, § 1207(e)(1)(A), title XIX, §§ 1903(a)(3), 1906(b)(13)(A), (C), Oct. 4, 1976, 90 Stat. 1706, 1807, 1834; Pub. L. 94–563, § 1(b), (c), Oct. 19, 1976, 90 Stat. 2655; Pub. L. 95–216, title III, §§ 312(a), (b), (d), (f), (g), 314(a), 315(a), 356(a)–(d), Dec. 20, 1977, 91 Stat. 1532–1536, 1555; Pub. L. 95–472, § 3(b), Oct. 17, 1978, 92 Stat. 1333; Pub. L. 95–600, title I, § 164(b)(3), Nov. 6, 1978, 92 Stat. 2814; Pub. L. 96–222, title I, § 101(a)(10)(B)(i), Apr. 1, 1980, 94 Stat. 201; Pub. L. 96–499, title XI, § 1141(a)(1), Dec. 5, 1980, 94 Stat. 2693; Pub. L. 97–34, title I, § 124(e)(2)(A), Aug. 13, 1981, 95 Stat. 200; Pub. L. 97–123, § 3(b), Dec. 29, 1981, 95 Stat. 1662; Pub. L. 97–248, title II, § 278(a)(1), Sept. 3, 1982, 96 Stat. 559; Pub. L. 98–21, title I, §§ 101(b), (c)(2), 102(b), title III, §§ 321(a), (e)(1), 322(a)(2), 323(a)(1), 324(a), 327(a)(1), (b)(1), 328(a), Apr. 20, 1983, 97 Stat. 69, 70, 118, 119, 121, 122, 126–128; Pub. L. 98–369, div. A, title I, § 67(c), title IV, § 491(d)(36), title V, § 531(d)(1)(A), div. B, title VI, §§ 2601(b), 2603(a)(2), (b), 2661(o)(3), 2663(i), (j)(5)(C), July 18, 1984, 98 Stat. 587, 851, 884, 1124, 1128, 1159, 1169, 1171; Pub. L. 99–221, § 3(b), Dec. 26, 1985, 99 Stat. 1735; Pub. L. 99–272, title XII, § 12112(b), title XIII, §§ 13205(a)(1), 13303(c)(2), Apr. 7, 1986, 100 Stat. 288, 313, 327; Pub. L. 99–335, title III, § 304(b), June 6, 1986, 100 Stat. 606; Pub. L. 99–509, title IX, § 9002(b)(1)(A), (2)(A), Oct. 21, 1986, 100 Stat. 1971; Pub. L. 99–514, title I, § 122(e)(1), title XI, §§ 1108(g)(7), 1147(b), 1151(d)(2)(A), title XVIII, §§ 1882(c), 1883(a)(11)(B), 1895(b)(18)(A), 1899A(38)–(40), Oct. 22, 1986, 100 Stat. 2112, 2435, 2494, 2505, 2915, 2916, 2935, 2960; Pub. L. 100–203, title IX, §§ 9001(b), 9002(b), 9003(a)(2), 9004(b), 9005(b), 9006(a), (b)(2), 9023(d), Dec. 22, 1987, 101 Stat. 1330–286 to 1330–289, 1330–296; Pub. L. 100–647, title I, §§ 1001(d)(2)(C)(i), (g)(4)(B)(i), 1011(e)(8), 1011B(a)(22)(A), (23)(A), 1018(r)(2)(A), (u)(35), title III, § 3043(c)(2), title VIII, §§ 8015(b)(2), (c)(2), 8016(a)(3)(A), (4)(A), (C), 8017(b), Nov. 10, 1988, 102 Stat. 3351, 3352, 3461, 3485, 3486, 3586, 3592, 3642, 3791–3793; Pub. L. 101–140, title II, § 203(a)(2), Nov. 8, 1989, 103 Stat. 830; Pub. L. 101–239, title X, § 10201(a), (b)(3), Dec. 19, 1989, 103 Stat. 2472; Pub. L. 101–508, title XI, §§ 11331(a), 11332(b), Nov. 5, 1990, 104 Stat. 1388–467, 1388–469; Pub. L. 101–650, title III, § 321, Dec. 1, 1990, 104 Stat. 5117; Pub. L. 102–318, title V, § 521(b)(34), July 3, 1992, 106 Stat. 312; Pub. L. 103–66, title XIII, § 13207(a), Aug. 10, 1993, 107 Stat. 467; Pub. L. 103–178, title II, § 204(c), Dec. 3, 1993, 107 Stat. 2033; Pub. L. 103–296, title I, § 108(h)(2), title III, §§ 303(a)(2), (b)(2), 319(a)(1), (5), 320(a)(1)(C), Aug. 15, 1994, 108 Stat. 1487, 1519, 1533–1535; Pub. L. 103–387, § 2(a)(1)(A)–(C), Oct. 22, 1994, 108 Stat. 4071; Pub. L. 104–188, title I, §§ 1116(a)(1)(A), (B), 1421(b)(8)(A), 1458(b)(1), Aug. 20, 1996, 110 Stat. 1762, 1798, 1819; Pub. L. 105–33, title XI, § 11246(b)(2)(A), as added Pub. L. 105–277, div. A, § 101(h) [title VIII, § 802(a)(2)], Oct. 21, 1998, 112 Stat. 2681–480, 2681–532; Pub. L. 105–61, title VI, § 642(d)(2), Oct. 10, 1997, 111 Stat. 1319; Pub. L. 105–206, title VI, § 6023(13), July 22, 1998, 112 Stat. 825; Pub. L. 106–554, § 1(a)(7) [title III, § 319(15)], Dec. 21, 2000, 114 Stat. 2763, 2763A–647; Pub. L. 108–121, title I, § 106(b)(2), Nov. 11, 2003, 117 Stat. 1339; Pub. L. 108–203, title IV, § 423(a), (c), Mar. 2, 2004, 118 Stat. 536; Pub. L. 108–357, title II, § 251(a)(1)(A), title III, § 320(b)(1), title VIII, § 802(c)(1), Oct. 22, 2004, 118 Stat. 1458, 1473, 1568; Pub. L. 108–375, div. A, title V, § 585(b)(2)(B), Oct. 28, 2004, 118 Stat. 1932; Pub. L. 109–280, title VIII, § 854(c)(8), Aug. 17, 2006, 120 Stat. 1018; Pub. L. 110–172, § 8(a)(2), Dec. 29, 2007, 121 Stat. 2483; Pub. L. 110–245, title I, § 115(a)(1), title III, § 302(a), June 17, 2008, 122 Stat. 1636, 1647; Pub. L. 110–458, title I, § 108(k)(1), Dec. 23, 2008, 122 Stat. 5110; Pub. L. 113–295, div. A, title II, § 221(a)(19)(B)(iv), (99)(C)(i), Dec. 19, 2014, 128 Stat. 4040, 4052; Pub. L. 115–141, div. U, title IV, § 401(a)(209), (210), (325)(A), Mar. 23, 2018, 132 Stat. 1194, 1199; Pub. L. 115–243, § 2(b)(2), Sept. 20, 2018, 132 Stat. 2895; Pub. L. 116–94, div. O, title III, § 301(c), Dec. 20, 2019, 133 Stat. 3175; Pub. L. 117–328, div. T, title VII, § 702(b)(1), Dec. 29, 2022, 136 Stat. 5404.)
A7: §199A | B7: (a)Allowance of deduction In the case of a taxpayer other than a corporation, except as provided in subsection (i), there shall be allowed as a deduction for any taxable year an amount equal to the lesser of— (1)the combined qualified business income amount of the taxpayer, or (2)an amount equal to 20 percent of the excess (if any) of— (A)the taxable income of the taxpayer for the taxable year, over (B)the net capital gain (as defined in section 1(h)) of the taxpayer for such taxable year. (b)Combined qualified business income amount For purposes of this section— (1)In general The term “combined qualified business income amount” means, with respect to any taxable year, an amount equal to— (A)the sum of the amounts determined under paragraph (2) for each qualified trade or business carried on by the taxpayer, plus (B)20 percent of the aggregate amount of the qualified REIT dividends and qualified publicly traded partnership income of the taxpayer for the taxable year. (2)Determination of deductible amount for each trade or business The amount determined under this paragraph with respect to any qualified trade or business is the lesser of— (A)20 percent of the taxpayer’s qualified business income with respect to the qualified trade or business, or (B)the greater of— (i)50 percent of the W–2 wages with respect to the qualified trade or business, or (ii)the sum of 25 percent of the W–2 wages with respect to the qualified trade or business, plus 2.5 percent of the unadjusted basis immediately after acquisition of all qualified property. (3)Modifications to limit based on taxable income (A)Exception from limit In the case of any taxpayer whose taxable income for the taxable year does not exceed the threshold amount, paragraph (2) shall be applied without regard to subparagraph (B). (B)Phase-in of limit for certain taxpayers (i)In general If— (I)the taxable income of a taxpayer for any taxable year exceeds the threshold amount, but does not exceed the sum of the threshold amount plus $75,000 ($150,000 in the case of a joint return), and (II)the amount determined under paragraph (2)(B) (determined without regard to this subparagraph) with respect to any qualified trade or business carried on by the taxpayer is less than the amount determined under paragraph (2)(A) with respect such trade or business, then paragraph (2) shall be applied with respect to such trade or business without regard to subparagraph (B) thereof and by reducing the amount determined under subparagraph (A) thereof by the amount determined under clause (ii). (ii)Amount of reduction The amount determined under this subparagraph is the amount which bears the same ratio to the excess amount as— (I)the amount by which the taxpayer’s taxable income for the taxable year exceeds the threshold amount, bears to (II)$75,000 ($150,000 in the case of a joint return). (iii)Excess amount For purposes of clause (ii), the excess amount is the excess of— (I)the amount determined under paragraph (2)(A) (determined without regard to this paragraph), over (II)the amount determined under paragraph (2)(B) (determined without regard to this paragraph). (4)Wages, etc. (A)In general The term “W–2 wages” means, with respect to any person for any taxable year of such person, the amounts described in paragraphs (3) and (8) of section 6051(a) paid by such person with respect to employment of employees by such person during the calendar year ending during such taxable year. (B)Limitation to wages attributable to qualified business income Such term shall not include any amount which is not properly allocable to qualified business income for purposes of subsection (c)(1). (C)Return requirement Such term shall not include any amount which is not properly included in a return filed with the Social Security Administration on or before the 60th day after the due date (including extensions) for such return. (5)Acquisitions, dispositions, and short taxable years The Secretary shall provide for the application of this subsection in cases of a short taxable year or where the taxpayer acquires, or disposes of, the major portion of a trade or business or the major portion of a separate unit of a trade or business during the taxable year. (6)Qualified property For purposes of this section: (A)In general The term “qualified property” means, with respect to any qualified trade or business for a taxable year, tangible property of a character subject to the allowance for depreciation under section 167— (i)which is held by, and available for use in, the qualified trade or business at the close of the taxable year, (ii)which is used at any point during the taxable year in the production of qualified business income, and (iii)the depreciable period for which has not ended before the close of the taxable year. (B)Depreciable period The term “depreciable period” means, with respect to qualified property of a taxpayer, the period beginning on the date the property was first placed in service by the taxpayer and ending on the later of— (i)the date that is 10 years after such date, or (ii)the last day of the last full year in the applicable recovery period that would apply to the property under section 168 (determined without regard to subsection (g) thereof). (7)Special rule with respect to income received from cooperatives In the case of any qualified trade or business of a patron of a specified agricultural or horticultural cooperative, the amount determined under paragraph (2) with respect to such trade or business shall be reduced by the lesser of— (A)9 percent of so much of the qualified business income with respect to such trade or business as is properly allocable to qualified payments received from such cooperative, or (B)50 percent of so much of the W–2 wages with respect to such trade or business as are so allocable. (c)Qualified business income For purposes of this section— (1)In general The term “qualified business income” means, for any taxable year, the net amount of qualified items of income, gain, deduction, and loss with respect to any qualified trade or business of the taxpayer. Such term shall not include any qualified REIT dividends or qualified publicly traded partnership income. (2)Carryover of losses If the net amount of qualified income, gain, deduction, and loss with respect to qualified trades or businesses of the taxpayer for any taxable year is less than zero, such amount shall be treated as a loss from a qualified trade or business in the succeeding taxable year. (3)Qualified items of income, gain, deduction, and loss For purposes of this subsection— (A)In general The term “qualified items of income, gain, deduction, and loss” means items of income, gain, deduction, and loss to the extent such items are— (i)effectively connected with the conduct of a trade or business within the United States (within the meaning of section 864(c), determined by substituting “qualified trade or business (within the meaning of section 199A)” for “nonresident alien individual or a foreign corporation” or for “a [1] foreign corporation” each place it appears), and (ii)included or allowed in determining taxable income for the taxable year. (B)Exceptions The following items shall not be taken into account as a qualified item of income, gain, deduction, or loss: (i)Any item of short-term capital gain, short-term capital loss, long-term capital gain, or long-term capital loss. (ii)Any dividend, income equivalent to a dividend, or payment in lieu of dividends described in section 954(c)(1)(G). Any amount described in section 1385(a)(1) shall not be treated as described in this clause. (iii)Any interest income other than interest income which is properly allocable to a trade or business. (iv)Any item of gain or loss described in subparagraph (C) or (D) of section 954(c)(1) (applied by substituting “qualified trade or business” for “controlled foreign corporation”). (v)Any item of income, gain, deduction, or loss taken into account under section 954(c)(1)(F) (determined without regard to clause (ii) thereof and other than items attributable to notional principal contracts entered into in transactions qualifying under section 1221(a)(7)). (vi)Any amount received from an annuity which is not received in connection with the trade or business. (vii)Any item of deduction or loss properly allocable to an amount described in any of the preceding clauses. (4)Treatment of reasonable compensation and guaranteed payments Qualified business income shall not include— (A)reasonable compensation paid to the taxpayer by any qualified trade or business of the taxpayer for services rendered with respect to the trade or business, (B)any guaranteed payment described in section 707(c) paid to a partner for services rendered with respect to the trade or business, (C)to the extent provided in regulations, any payment described in section 707(a) to a partner for services rendered with respect to the trade or business, and (D)any amount with respect to which a deduction is allowable to the taxpayer under section 224(a) for the taxable year. (d)Qualified trade or business For purposes of this section— (1)In general The term “qualified trade or business” means any trade or business other than— (A)a specified service trade or business, or (B)the trade or business of performing services as an employee. (2)Specified service trade or business The term “specified service trade or business” means any trade or business— (A)which is described in section 1202(e)(3)(A) (applied without regard to the words “engineering, architecture,”) or which would be so described if the term “employees or owners” were substituted for “employees” therein, or (B)which involves the performance of services that consist of investing and investment management, trading, or dealing in securities (as defined in section 475(c)(2)), partnership interests, or commodities (as defined in section 475(e)(2)). (3)Exception for specified service businesses based on taxpayer’s income (A)In general If, for any taxable year, the taxable income of any taxpayer is less than the sum of the threshold amount plus $75,000 ($150,000 in the case of a joint return), then— (i)any specified service trade or business of the taxpayer shall not fail to be treated as a qualified trade or business due to paragraph (1)(A), but (ii)only the applicable percentage of qualified items of income, gain, deduction, or loss, and the W–2 wages and the unadjusted basis immediately after acquisition of qualified property, of the taxpayer allocable to such specified service trade or business shall be taken into account in computing the qualified business income, W–2 wages, and the unadjusted basis immediately after acquisition of qualified property of the taxpayer for the taxable year for purposes of applying this section. (B)Applicable percentage For purposes of subparagraph (A), the term “applicable percentage” means, with respect to any taxable year, 100 percent reduced (not below zero) by the percentage equal to the ratio of— (i)the taxable income of the taxpayer for the taxable year in excess of the threshold amount, bears to (ii)$75,000 ($150,000 in the case of a joint return). (e)Other definitions For purposes of this section— (1)Taxable income Except as otherwise provided in subsection (g)(2)(B), taxable income shall be computed without regard to section 68 and without regard to any deduction allowable under this section. (2)Threshold amount (A)In general The term “threshold amount” means $157,500 (200 percent of such amount in the case of a joint return). (B)Inflation adjustment In the case of any taxable year beginning after 2018, the dollar amount in subparagraph (A) shall be increased by an amount equal to— (i)such dollar amount, multiplied by (ii)the cost-of-living adjustment determined under section 1(f)(3) for the calendar year in which the taxable year begins, determined by substituting “calendar year 2017” for “calendar year 2016” in subparagraph (A)(ii) thereof. The amount of any increase under the preceding sentence shall be rounded as provided in section 1(f)(7). (3)Qualified REIT dividend The term “qualified REIT dividend” means any dividend from a real estate investment trust received during the taxable year which— (A)is not a capital gain dividend, as defined in section 857(b)(3), and (B)is not qualified dividend income, as defined in section 1(h)(11). (4)Qualified publicly traded partnership income The term “qualified publicly traded partnership income” means, with respect to any qualified trade or business of a taxpayer, the sum of— (A)the net amount of such taxpayer’s allocable share of each qualified item of income, gain, deduction, and loss (as defined in subsection (c)(3) and determined after the application of subsection (c)(4)) from a publicly traded partnership (as defined in section 7704(a)) [2] which is not treated as a corporation under section 7704(c), plus (B)any gain recognized by such taxpayer upon disposition of its interest in such partnership to the extent such gain is treated as an amount realized from the sale or exchange of property other than a capital asset under section 751(a). (f)Special rules (1)Application to partnerships and S corporations (A)In general In the case of a partnership or S corporation— (i)this section shall be applied at the partner or shareholder level, (ii)each partner or shareholder shall take into account such person’s allocable share of each qualified item of income, gain, deduction, and loss, and (iii)each partner or shareholder shall be treated for purposes of subsection (b) as having W–2 wages and unadjusted basis immediately after acquisition of qualified property for the taxable year in an amount equal to such person’s allocable share of the W–2 wages and the unadjusted basis immediately after acquisition of qualified property of the partnership or S corporation for the taxable year (as determined under regulations prescribed by the Secretary). For purposes of clause (iii), a partner’s or shareholder’s allocable share of W–2 wages shall be determined in the same manner as the partner’s or shareholder’s allocable share of wage expenses. For purposes of such clause, partner’s or shareholder’s allocable share of the unadjusted basis immediately after acquisition of qualified property shall be determined in the same manner as the partner’s or shareholder’s allocable share of depreciation. For purposes of this subparagraph, in the case of an S corporation, an allocable share shall be the shareholder’s pro rata share of an item. (B)Application to trusts and estates Rules similar to the rules under section 199(d)(1)(B)(i) (as in effect on December 1, 2017) for the apportionment of W–2 wages shall apply to the apportionment of W–2 wages and the apportionment of unadjusted basis immediately after acquisition of qualified property under this section. (C)Treatment of trades or business in Puerto Rico (i)In general In the case of any taxpayer with qualified business income from sources within the commonwealth of Puerto Rico, if all such income is taxable under section 1 for such taxable year, then for purposes of determining the qualified business income of such taxpayer for such taxable year, the term “United States” shall include the Commonwealth of Puerto Rico. (ii)Special rule for applying limit In the case of any taxpayer described in clause (i), the determination of W–2 wages of such taxpayer with respect to any qualified trade or business conducted in Puerto Rico shall be made without regard to any exclusion under section 3401(a)(8) for remuneration paid for services in Puerto Rico. (2)Coordination with minimum tax For purposes of determining alternative minimum taxable income under section 55, qualified business income shall be determined without regard to any adjustments under sections 56 through 59. (3)Deduction limited to income taxes The deduction under subsection (a) shall only be allowed for purposes of this chapter. (4)Regulations The Secretary shall prescribe such regulations as are necessary to carry out the purposes of this section, including regulations— (A)for requiring or restricting the allocation of items and wages under this section and such reporting requirements as the Secretary determines appropriate, and (B)for the application of this section in the case of tiered entities. (g)Deduction for income attributable to domestic production activities of specified agricultural or horticultural cooperatives (1)Allowance of deduction (A)In general In the case of a taxpayer which is a specified agricultural or horticultural cooperative, there shall be allowed as a deduction an amount equal to 9 percent of the lesser of— (i)the qualified production activities income of the taxpayer for the taxable year, or (ii)the taxable income of the taxpayer for the taxable year. (B)Limitation (i)In general The deduction allowable under subparagraph (A) for any taxable year shall not exceed 50 percent of the W–2 wages of the taxpayer for the taxable year. (ii)W–2 wages For purposes of this subparagraph, the W–2 wages of the taxpayer shall be determined in the same manner as under subsection (b)(4) (without regard to subparagraph (B) thereof and after application of subsection (b)(5)), except that such wages shall not include any amount which is not properly allocable to domestic production gross receipts for purposes of paragraph (3)(A). (C)Taxable income of cooperatives determined without regard to certain deductions For purposes of this subsection, the taxable income of a specified agricultural or horticultural cooperative shall be computed without regard to any deduction allowable under subsection (b) or (c) of section 1382 (relating to patronage dividends, per-unit retain allocations, and nonpatronage distributions). (2)Deduction allowed to patrons (A)In general In the case of any eligible taxpayer who receives a qualified payment from a specified agricultural or horticultural cooperative, there shall be allowed as a deduction for the taxable year in which such payment is received an amount equal to the portion of the deduction allowed under paragraph (1) to such cooperative which is— (i)allowed with respect to the portion of the qualified production activities income to which such payment is attributable, and (ii)identified by such cooperative in a written notice mailed to such taxpayer during the payment period described in section 1382(d). (B)Limitation based on taxable income The deduction allowed to any taxpayer under this paragraph shall not exceed the taxable income of the taxpayer determined without regard to section 68 or the deduction allowed under this paragraph and after taking into account any deduction allowed to the taxpayer under subsection (a) for the taxable year. (C)Cooperative denied deduction for portion of qualified payments The taxable income of a specified agricultural or horticultural cooperative shall not be reduced under section 1382 by reason of that portion of any qualified payment as does not exceed the deduction allowable under subparagraph (A) with respect to such payment. (D)Eligible taxpayer For purposes of this paragraph, the term “eligible taxpayer” means— (i)a taxpayer other than a corporation, or (ii)a specified agricultural or horticultural cooperative. (E)Qualified payment For purposes of this section, the term “qualified payment” means, with respect to any eligible taxpayer, any amount which— (i)is described in paragraph (1) or (3) of section 1385(a), (ii)is received by such taxpayer from a specified agricultural or horticultural cooperative, and (iii)is attributable to qualified production activities income with respect to which a deduction is allowed to such cooperative under paragraph (1). (3)Qualified production activities income For purposes of this subsection— (A)In general The term “qualified production activities income” for any taxable year means an amount equal to the excess (if any) of— (i)the taxpayer’s domestic production gross receipts for such taxable year, over (ii)the sum of— (I)the cost of goods sold that are allocable to such receipts, and (II)other expenses, losses, or deductions (other than the deduction allowed under this subsection), which are properly allocable to such receipts. (B)Allocation method The Secretary shall prescribe rules for the proper allocation of items described in subparagraph (A) for purposes of determining qualified production activities income. Such rules shall provide for the proper allocation of items whether or not such items are directly allocable to domestic production gross receipts. (C)Special rules for determining costs (i)In general For purposes of determining costs under subclause (I) of subparagraph (A)(ii), any item or service brought into the United States shall be treated as acquired by purchase, and its cost shall be treated as not less than its value immediately after it entered the United States. A similar rule shall apply in determining the adjusted basis of leased or rented property where the lease or rental gives rise to domestic production gross receipts. (ii)Exports for further manufacture In the case of any property described in clause (i) that had been exported by the taxpayer for further manufacture, the increase in cost or adjusted basis under clause (i) shall not exceed the difference between the value of the property when exported and the value of the property when brought back into the United States after the further manufacture. (D)Domestic production gross receipts (i)In general The term “domestic production gross receipts” means the gross receipts of the taxpayer which are derived from any lease, rental, license, sale, exchange, or other disposition of any agricultural or horticultural product which was manufactured, produced, grown, or extracted by the taxpayer (determined after the application of paragraph (4)(B)) in whole or significant part within the United States. Such term shall not include gross receipts of the taxpayer which are derived from the lease, rental, license, sale, exchange, or other disposition of land. (ii)Related persons (I)In general The term “domestic production gross receipts” shall not include any gross receipts of the taxpayer derived from property leased, licensed, or rented by the taxpayer for use by any related person. (II)Related person For purposes of subclause (I), a person shall be treated as related to another person if such persons are treated as a single employer under subsection (a) or (b) of section 52 or subsection (m) or (o) of section 414, except that determinations under subsections (a) and (b) of section 52 shall be made without regard to section 1563(b). (4)Specified agricultural or horticultural cooperative For purposes of this section— (A)In general The term “specified agricultural or horticultural cooperative” means an organization to which part I of subchapter T applies which is engaged— (i)in the manufacturing, production, growth, or extraction in whole or significant part of any agricultural or horticultural product, or (ii)in the marketing of agricultural or horticultural products. (B)Application to marketing cooperatives A specified agricultural or horticultural cooperative described in subparagraph (A)(ii) shall be treated as having manufactured, produced, grown, or extracted in whole or significant part any agricultural or horticultural product marketed by the specified agricultural or horticultural cooperative which its patrons have so manufactured, produced, grown, or extracted. (5)Definitions and special rules (A)Special rule for affiliated groups (i)In general All members of an expanded affiliated group shall be treated as a single corporation for purposes of this subsection. (ii)Partnerships owned by expanded affiliated groups For purposes of paragraph (3)(D), if all of the interests in the capital and profits of a partnership are owned by members of a single expanded affiliated group at all times during the taxable year of such partnership, the partnership and all members of such group shall be treated as a single taxpayer during such period. (iii)Expanded affiliated group For purposes of this subsection, the term “expanded affiliated group” means an affiliated group as defined in section 1504(a), determined— (I)by substituting “more than 50 percent” for “at least 80 percent” each place it appears, and (II)without regard to paragraphs (2) and (4) of section 1504(b). (iv)Allocation of deduction Except as provided in regulations, the deduction under paragraph (1) shall be allocated among the members of the expanded affiliated group in proportion to each member’s respective amount (if any) of qualified production activities income. (B)Special rule for cooperative partners In the case of a specified agricultural or horticultural cooperative which is a partner in a partnership, rules similar to the rules of subsection (f)(1) shall apply for purposes of this subsection. (C)Trade or business requirement This subsection shall be applied by only taking into account items which are attributable to the actual conduct of a trade or business. (D)Unrelated business taxable income For purposes of determining the tax imposed by section 511, this section shall be applied by substituting “unrelated business taxable income” for “taxable income” each place it appears in this section (other than this subparagraph). (E)Special rule for cooperative with oil related qualified production activities income (i)In general If a specified agricultural or horticultural cooperative has oil related qualified production activities income for any taxable year, the amount otherwise allowable as a deduction under paragraph (1) shall be reduced by 3 percent of the least of— (I)the oil related qualified production activities income of the cooperative for the taxable year, (II)the qualified production activities income of the cooperative for the taxable year, or (III)taxable income. (ii)Oil related qualified production activities income For purposes of this subparagraph, the term “oil related qualified production activities income” means for any taxable year the qualified production activities income which is attributable to the production, refining, processing, transportation, or distribution of oil, gas, or any primary product thereof (within the meaning of section 927(a)(2)(C), as in effect before its repeal) during such taxable year. (6)Regulations The Secretary shall prescribe such regulations as are necessary to carry out the purposes of this subsection, including regulations which prevent more than 1 taxpayer from being allowed a deduction under this subsection with respect to any activity described in paragraph (3)(D)(i). Such regulations shall be based on the regulations applicable to cooperatives and their patrons under section 199 (as in effect before its repeal). (h)Anti-abuse rules The Secretary shall— (1)apply rules similar to the rules under section 179(d)(2) in order to prevent the manipulation of the depreciable period of qualified property using transactions between related parties, and (2)prescribe rules for determining the unadjusted basis immediately after acquisition of qualified property acquired in like-kind exchanges or involuntary conversions. (i)Minimum deduction for active qualified business income (1)In general In the case of an applicable taxpayer for any taxable year, the deduction allowed under subsection (a) for the taxable year shall be equal to the greater of— (A)the amount of such deduction determined without regard to this subsection, or (B)$400. (2)Applicable taxpayer For purposes of this subsection— (A)In general The term “applicable taxpayer” means, with respect to any taxable year, a taxpayer whose aggregate qualified business income with respect to all active qualified trades or businesses of the taxpayer for such taxable year is at least $1,000. (B)Active qualified trade or business The term “active qualified trade or business” means, with respect to any taxpayer for any taxable year, any qualified trade or business of the taxpayer in which the taxpayer materially participates (within the meaning of section 469(h)). (3)Inflation adjustment In the case of any taxable year beginning after 2026, the $400 amount in paragraph (1)(B) and the $1,000 amount in paragraph (2)(A) shall each be increased by an amount equal to— (A)such dollar amount, multiplied by (B)the cost-of-living adjustment determined under section 1(f)(3) for the calendar year in which the taxable year begins, determined by substituting “calendar year 2025” for “calendar year 2016” in subparagraph (A)(ii) thereof. If any increase under this paragraph is not a multiple of $5, such increase shall be rounded to the nearest multiple of $5 (Added Pub. L. 115–97, title I, § 11011(a), Dec. 22, 2017, 131 Stat. 2063; amended Pub. L. 115–141, div. T, § 101(a)(1), (2)(A), (C), (b), Mar. 23, 2018, 132 Stat. 1151, 1155; Pub. L. 119–21, title VII, §§ 70105(a), (b), 70111(b), 70201(d), July 4, 2025, 139 Stat. 161, 165, 171.) | C7: =IFERROR(__xludf.DUMMYFUNCTION("GEMINI(""Summarize IRC §199A in exactly 1 sentence under 20 words. Focus on the 20% QBI deduction and who qualifies. Text: ""&B7)"),"Eligible pass-through business owners can deduct up to 20% of their qualified business income from their taxable income.") -> Eligible pass-through business owners can deduct up to 20% of their qualified business income from their taxable income. | D7: =IFERROR(__xludf.DUMMYFUNCTION("GEMINI(""List 3-5 industries and 2-3 entity types most affected. Format exactly: Industries: [x,y,z] | Entities: [a,b,c]. Text: ""&B7)"),"Industries: [Agriculture, Manufacturing, Real Estate, Professional Services, Retail] | Entities: [S Corporations, Partnerships, Sole Proprietorships]") -> Industries: [Agriculture, Manufacturing, Real Estate, Professional Services, Retail] | Entities: [S Corporations, Partnerships, Sole Proprietorships] | E7: =IFERROR(__xludf.DUMMYFUNCTION("GEMINI(""What QuickBooks data fields check if §199A applies? List comma-separated accounts: net income, W-2 wages, qualified property. Text: ""&B7)"),"Net Income, W-2 Wages, Qualified Property (UBIA), Fixed Asset Accounts, Partner/Shareholder Distributions, Chart of Accounts (Entity Type), Cost of Goods Sold, Business Expenses") -> Net Income, W-2 Wages, Qualified Property (UBIA), Fixed Asset Accounts, Partner/Shareholder Distributions, Chart of Accounts (Entity Type), Cost of Goods Sold, Business Expenses | F7: 🚨 Important: Qualified Business Income Deduction Update for [Entity] How this affects you: Great news\! Based on your [QBI_Amount] in qualified business income, your entity may be eligible for a deduction of up to 20%, estimated at [Deduction_Estimate]. This deduction can significantly reduce your taxable income. Please note that if your business is a Specified Service Trade or Business (SSTB), the deduction may be limited or phased out based on your total taxable income and the \[W2_Wages] paid by the business. ✅ Verify if your total taxable income is below the threshold for the full 20% deduction ✅ Review your \[W2_Wages] and unadjusted basis immediately after acquisition (UBIA) of qualified property to determine if wage and property limitations apply ✅ Consult with a CPA to confirm your business classification and maximize your eligible deduction 📚 Source: IRC Section 199A ⚠️ Disclaimer: This template is for informational purposes only. Tax laws are subject to change and individual circumstances vary. Please consult with a qualified tax professional to confirm eligibility and compliance for your specific entity. | G7: =IFERROR(__xludf.DUMMYFUNCTION("GEMINI(""Explain in 1 sentence how §199A impacts Effective Tax Rate or Owner Equity ratios. For a non-accountant CFO. Text: ""&B7)"),"IRC Section 199A provides a deduction of up to 20% of qualified business income for pass-through entities, which effectively lowers your business's tax rate and increases retained owner equity.") -> IRC Section 199A provides a deduction of up to 20% of qualified business income for pass-through entities, which effectively lowers your business's tax rate and increases retained owner equity.
A8: §174 | B8: (a)In general In the case of a taxpayer’s foreign research or experimental expenditures for any taxable year— (1)except as provided in paragraph (2), no deduction shall be allowed for such expenditures, and (2)the taxpayer shall— (A)charge such expenditures to capital account, and (B)be allowed an amortization deduction of such expenditures ratably over the 15-year period beginning with the midpoint of the taxable year in which such expenditures are paid or incurred. (b)Foreign research or experimental expenditures For purposes of this section, the term “foreign research or experimental expenditures” means, with respect to any taxable year, research or experimental expenditures which are paid or incurred by the taxpayer during such taxable year in connection with the taxpayer’s trade or business and which are attributable to foreign research (within the meaning of section 41(d)(4)(F)). (c)Special rules (1)Land and other property This section shall not apply to any expenditure for the acquisition or improvement of land, or for the acquisition or improvement of property to be used in connection with the research or experimentation and of a character which is subject to the allowance under section 167 (relating to allowance for depreciation, etc.) or section 611 (relating to allowance for depletion); but for purposes of this section allowances under section 167, and allowances under section 611, shall be considered as expenditures. (2)Exploration expenditures This section shall not apply to any expenditure paid or incurred for the purpose of ascertaining the existence, location, extent, or quality of any deposit of ore or other mineral (including oil and gas). (3)Software development For purposes of this section, any amount paid or incurred in connection with the development of any software shall be treated as a research or experimental expenditure. (d)Treatment upon disposition, retirement, or abandonment If any property with respect to which foreign research or experimental expenditures are paid or incurred is disposed, retired, or abandoned during the period during which such expenditures are allowed as an amortization deduction under this section, no deduction or reduction to amount realized shall be allowed with respect to such expenditures on account of such disposition, retirement, or abandonment and such amortization deduction shall continue with respect to such expenditures. (Aug. 16, 1954, ch. 736, 68A Stat. 66; Pub. L. 94–455, title XIX, §§ 1901(a)(30), 1906(b)(13)(A), Oct. 4, 1976, 90 Stat. 1769, 1834; Pub. L. 97–248, title II, § 201(d)(9)(B) formerly § 201(c)(9)(B), Sept. 3, 1982, 96 Stat. 420, renumbered § 201(d)(9)(B), Pub. L. 97–448, title III, § 306(a)(1)(A)(i), Jan. 12, 1983, 96 Stat. 2400; amended Pub. L. 99–514, title VII, § 701(e)(4)(D), Oct. 22, 1986, 100 Stat. 2343; Pub. L. 100–647, title I, § 1007(g)(5), Nov. 10, 1988, 102 Stat. 3435; Pub. L. 101–239, title VII, § 7110(d), Dec. 19, 1989, 103 Stat. 2325; Pub. L. 113–295, div. A, title II, § 221(a)(31), (32), Dec. 19, 2014, 128 Stat. 4042; Pub. L. 115–97, title I, § 13206(a), Dec. 22, 2017, 131 Stat. 2111; Pub. L. 119–21, title VII, § 70302(b)(1), July 4, 2025, 139 Stat. 191.) | C8: =IFERROR(__xludf.DUMMYFUNCTION("GEMINI(""Summarize IRC §174 in exactly 1 sentence under 20 words. Focus on the amortization of research and experimental expenditures. Text: ""&B8)"),"Foreign research and experimental expenditures must be capitalized and amortized over a 15-year period.") -> Foreign research and experimental expenditures must be capitalized and amortized over a 15-year period. | D8: =IFERROR(__xludf.DUMMYFUNCTION("GEMINI(""List 3-5 industries and 2-3 entity types most affected. Format exactly: Industries: [x,y,z] | Entities: [a,b,c]. Text: ""&B8)"),"Industries: [Biotechnology, Software Development, Pharmaceuticals, Technology, Manufacturing] | Entities: [Corporations, Partnerships, Limited Liability Companies]") -> Industries: [Biotechnology, Software Development, Pharmaceuticals, Technology, Manufacturing] | Entities: [Corporations, Partnerships, Limited Liability Companies] | E8: =IFERROR(__xludf.DUMMYFUNCTION("GEMINI(""What QuickBooks data fields check if §174 applies? List comma-separated fields or reports. Text: ""&B8)"),"Payroll Expenses, Contractor/Consultant Fees, Supplies Expense, Software Development Costs, R&D Asset Account, Accumulated Amortization, Amortization Expense, Chart of Accounts, General Ledger Report, Project/Job Profitability Reports") -> Payroll Expenses, Contractor/Consultant Fees, Supplies Expense, Software Development Costs, R&D Asset Account, Accumulated Amortization, Amortization Expense, Chart of Accounts, General Ledger Report, Project/Job Profitability Reports | F8: 🚨 Important: Foreign R&D Capitalization Update for [Entity] How this affects you: IRC Section 174 requires that all foreign research and experimental expenditures, including software development costs, must be capitalized rather than deducted immediately. These expenses must now be amortized ratably over a 15-year period, beginning with the midpoint of the taxable year in which they were incurred. ✅ Identify all foreign-based research, software development, and experimental expenditures ✅ Ensure these costs are moved to a capital account for proper amortization tracking ✅ Update your tax projections to account for the longer 15-year recovery period for foreign R\&D 📚 Source: IRC Section 174 ⚠️ Disclaimer: This template is for informational purposes only. Tax laws are subject to change and individual circumstances vary. Please consult with a qualified tax professional to confirm eligibility and compliance for your specific entity. | G8: =IFERROR(__xludf.DUMMYFUNCTION("GEMINI(""Explain in 1 sentence how §174 impacts cash flow or tax ratios. For a non-accountant CFO. Text: ""&B8)"),"IRC Section 174 requires foreign research and software development costs to be capitalized and amortized over 15 years, which reduces immediate tax deductions and negatively impacts short-term cash flow compared to full expensing.") -> IRC Section 174 requires foreign research and software development costs to be capitalized and amortized over 15 years, which reduces immediate tax deductions and negatively impacts short-term cash flow compared to full expensing.
A9: §263A | B9: (a)Nondeductibility of certain direct and indirect costs (1)In general In the case of any property to which this section applies, any costs described in paragraph (2)— (A)in the case of property which is inventory in the hands of the taxpayer, shall be included in inventory costs, and (B)in the case of any other property, shall be capitalized. (2)Allocable costs The costs described in this paragraph with respect to any property are— (A)the direct costs of such property, and (B)such property’s proper share of those indirect costs (including taxes) part or all of which are allocable to such property. Any cost which (but for this subsection) could not be taken into account in computing taxable income for any taxable year shall not be treated as a cost described in this paragraph. (b)Property to which section applies Except as otherwise provided in this section, this section shall apply to— (1)Property produced by taxpayer Real or tangible personal property produced by the taxpayer. (2)Property acquired for resale Real or personal property described in section 1221(a)(1) which is acquired by the taxpayer for resale. For purposes of paragraph (1), the term “tangible personal property” shall include a film, sound recording, video tape, book, or similar property. (c)General exceptions (1)Personal use property This section shall not apply to any property produced by the taxpayer for use by the taxpayer other than in a trade or business or an activity conducted for profit. (2)Research and experimental expenditures This section shall not apply to any amount allowable as a deduction under section 174 or 174A. (3)Certain development and other costs of oil and gas wells or other mineral property This section shall not apply to any cost allowable as a deduction under section 167(h), 179B, 263(c), 263(i), 291(b)(2), 616, or 617. (4)Coordination with long-term contract rules This section shall not apply to any property produced by the taxpayer pursuant to a long-term contract. (5)Timber and certain ornamental trees This section shall not apply to— (A)trees raised, harvested, or grown by the taxpayer other than trees described in clause (ii) of subsection (e)(4)(B) (after application of the last sentence thereof), and (B)any real property underlying such trees. (6)Coordination with section 59(e) Paragraphs (2) and (3) shall apply to any amount allowable as a deduction under section 59(e) for qualified expenditures described in subparagraphs (B), (C), (D), and (E) of paragraph (2) thereof. (7)Coordination with section 168(k)(5) This section shall not apply to any amount allowed as a deduction by reason of section 168(k)(5) (relating to special rules for certain plants bearing fruits and nuts). (d)Exception for farming businesses (1)Section not to apply to certain property (A)In general This section shall not apply to any of the following which is produced by the taxpayer in a farming business: (i)Any animal. (ii)Any plant which has a preproductive period of 2 years or less. (B)Exception for taxpayers required to use accrual method Subparagraph (A) shall not apply to any corporation, partnership, or tax shelter required to use an accrual method of accounting under section 447 or 448(a)(3). (2)Treatment of certain plants lost by reason of casualty (A)In general If plants bearing an edible crop for human consumption were lost or damaged (while in the hands of the taxpayer) by reason of freezing temperatures, disease, drought, pests, or casualty, this section shall not apply to any costs of the taxpayer of replanting plants bearing the same type of crop (whether on the same parcel of land on which such lost or damaged plants were located or any other parcel of land of the same acreage in the United States). (B)Special rule for person with minority interest who materially participates Subparagraph (A) shall apply to amounts paid or incurred by a person (other than the taxpayer described in subparagraph (A)) if— (i)the taxpayer described in subparagraph (A) has an equity interest of more than 50 percent in the plants described in subparagraph (A) at all times during the taxable year in which such amounts were paid or incurred, and (ii)such other person holds any part of the remaining equity interest and materially participates in the planting, maintenance, cultivation, or development of the plants described in subparagraph (A) during the taxable year in which such amounts were paid or incurred. The determination of whether an individual materially participates in any activity shall be made in a manner similar to the manner in which such determination is made under section 2032A(e)(6). (C)Special temporary rule for citrus plants lost by reason of casualty (i)In general In the case of the replanting of citrus plants, subparagraph (A) shall apply to amounts paid or incurred by a person (other than the taxpayer described in subparagraph (A)) if— (I)the taxpayer described in subparagraph (A) has an equity interest of not less than 50 percent in the replanted citrus plants at all times during the taxable year in which such amounts were paid or incurred and such other person holds any part of the remaining equity interest, or (II)such other person acquired the entirety of such taxpayer’s equity interest in the land on which the lost or damaged citrus plants were located at the time of such loss or damage, and the replanting is on such land. (ii)Termination Clause (i) shall not apply to any cost paid or incurred after the date which is 10 years after the date of the enactment of the Tax Cuts and Jobs Act. (3)Election to have this section not apply (A)In general If a taxpayer makes an election under this paragraph, this section shall not apply to any plant produced in any farming business carried on by such taxpayer. (B)Certain persons not eligible No election may be made under this paragraph by a corporation, partnership, or tax shelter, if such corporation, partnership, or tax shelter is required to use an accrual method of accounting under section 447 or 448(a)(3). (C)Special rule for citrus and almond growers An election under this paragraph shall not apply with respect to any item which is attributable to the planting, cultivation, maintenance, or development of any citrus or almond grove (or part thereof) and which is incurred before the close of the 4th taxable year beginning with the taxable year in which the trees were planted. For purposes of the preceding sentence, the portion of a citrus or almond grove planted in 1 taxable year shall be treated separately from the portion of such grove planted in another taxable year. (D)Election Unless the Secretary otherwise consents, an election under this paragraph may be made only for the taxpayer’s 1st taxable year which begins after December 31, 1986, and during which the taxpayer engages in a farming business. Any such election, once made, may be revoked only with the consent of the Secretary. (e)Definitions and special rules for purposes of subsection (d) (1)Recapture of expensed amounts on disposition (A)In general In the case of any plant with respect to which amounts would have been capitalized under subsection (a) but for an election under subsection (d)(3)— (i)such plant (if not otherwise section 1245 property) shall be treated as section 1245 property, and (ii)for purposes of section 1245, the recapture amount shall be treated as a deduction allowed for depreciation with respect to such property. (B)Recapture amount For purposes of subparagraph (A), the term “recapture amount” means any amount allowable as a deduction to the taxpayer which, but for an election under subsection (d)(3), would have been capitalized with respect to the plant. (2)Effects of election on depreciation (A)In general If the taxpayer (or any related person) makes an election under subsection (d)(3), the provisions of section 168(g)(2) (relating to alternative depreciation) shall apply to all property of the taxpayer used predominantly in the farming business and placed in service in any taxable year during which any such election is in effect. (B)Related person For purposes of subparagraph (A), the term “related person” means— (i)the taxpayer and members of the taxpayer’s family, (ii)any corporation (including an S corporation) if 50 percent or more (in value) of the stock of such corporation is owned (directly or through the application of section 318) by the taxpayer or members of the taxpayer’s family, (iii)a corporation and any other corporation which is a member of the same controlled group described in section 1563(a)(1), and (iv)any partnership if 50 percent or more (in value) of the interests in such partnership is owned directly or indirectly by the taxpayer or members of the taxpayer’s family. (C)Members of family For purposes of this paragraph, the term “family” means the taxpayer, the spouse of the taxpayer, and any of their children who have not attained age 18 before the close of the taxable year. (3)Preproductive period (A)In general For purposes of this section, the term “preproductive period” means— (i)in the case of a plant which will have more than 1 crop or yield, the period before the 1st marketable crop or yield from such plant, or (ii)in the case of any other plant, the period before such plant is reasonably expected to be disposed of. For purposes of this subparagraph, use by the taxpayer in a farming business of any supply produced in such business shall be treated as a disposition. (B)Rule for determining period In the case of a plant grown in commercial quantities in the United States, the preproductive period for such plant if grown in the United States shall be based on the nationwide weighted average preproductive period for such plant. (4)Farming business For purposes of this section— (A)In general The term “farming business” means the trade or business of farming. (B)Certain trades and businesses included The term “farming business” shall include the trade or business of— (i)operating a nursery or sod farm, or (ii)the raising or harvesting of trees bearing fruit, nuts, or other crops, or ornamental trees. For purposes of clause (ii), an evergreen tree which is more than 6 years old at the time severed from the roots shall not be treated as an ornamental tree. (5)Certain inventory valuation methods permitted The Secretary shall by regulations permit the taxpayer to use reasonable inventory valuation methods to compute the amount required to be capitalized under subsection (a) in the case of any plant. (f)Special rules for allocation of interest to property produced by the taxpayer (1)Interest capitalized only in certain cases Subsection (a) shall only apply to interest costs which are— (A)paid or incurred during the production period, and (B)allocable to property which is described in subsection (b)(1) and which has— (i)a long useful life, (ii)an estimated production period exceeding 2 years, or (iii)an estimated production period exceeding 1 year and a cost exceeding $1,000,000. (2)Allocation rules (A)In general In determining the amount of interest required to be capitalized under subsection (a) with respect to any property— (i)interest on any indebtedness directly attributable to production expenditures with respect to such property shall be assigned to such property, and (ii)interest on any other indebtedness shall be assigned to such property to the extent that the taxpayer’s interest costs could have been reduced if production expenditures (not attributable to indebtedness described in clause (i)) had not been incurred. (B)Exception for qualified residence interest Subparagraph (A) shall not apply to any qualified residence interest (within the meaning of section 163(h)). (C)Special rule for flow-through entities Except as provided in regulations, in the case of any flow-through entity, this paragraph shall be applied first at the entity level and then at the beneficiary level. (3)Interest relating to property used to produce property This subsection shall apply to any interest on indebtedness allocable (as determined under paragraph (2)) to property used to produce property to which this subsection applies to the extent such interest is allocable (as so determined) to the produced property. (4)Exemption for aging process of beer, wine, and distilled spirits For purposes of this subsection, the production period shall not include the aging period for— (A)beer (as defined in section 5052(a)), (B)wine (as described in section 5041(a)), or (C)distilled spirits (as defined in section 5002(a)(8)), except such spirits that are unfit for use for beverage purposes. (5)Definitions For purposes of this subsection— (A)Long useful life Property has a long useful life if such property is— (i)real property, or (ii)property with a class life of 20 years or more (as determined under section 168). (B)Production period The term “production period” means, when used with respect to any property, the period— (i)beginning on the date on which production of the property begins, and (ii)except as provided in paragraph (4), ending on the date on which the property is ready to be placed in service or is ready to be held for sale. (C)Production expenditures The term “production expenditures” means the costs (whether or not incurred during the production period) required to be capitalized under subsection (a) with respect to the property. (g)Production For purposes of this section— (1)In general The term “produce” includes construct, build, install, manufacture, develop, or improve. (2)Treatment of property produced under contract for the taxpayer The taxpayer shall be treated as producing any property produced for the taxpayer under a contract with the taxpayer; except that only costs paid or incurred by the taxpayer (whether under such contract or otherwise) shall be taken into account in applying subsection (a) to the taxpayer. (h)Exemption for free lance authors, photographers, and artists (1)In general Nothing in this section shall require the capitalization of any qualified creative expense. (2)Qualified creative expense For purposes of this subsection, the term “qualified creative expense” means any expense— (A)which is paid or incurred by an individual in the trade or business of such individual (other than as an employee) of being a writer, photographer, or artist, and (B)which, without regard to this section, would be allowable as a deduction for the taxable year. Such term does not include any expense related to printing, photographic plates, motion picture films, video tapes, or similar items. (3)Definitions For purposes of this subsection— (A)Writer The term “writer” means any individual if the personal efforts of such individual create (or may reasonably be expected to create) a literary manuscript, musical composition (including any accompanying words), or dance score. (B)Photographer The term “photographer” means any individual if the personal efforts of such individual create (or may reasonably be expected to create) a photograph or photographic negative or transparency. (C)Artist (i)In general The term “artist” means any individual if the personal efforts of such individual create (or may reasonably be expected to create) a picture, painting, sculpture, statue, etching, drawing, cartoon, graphic design, or original print edition. (ii)Criteria In determining whether any expense is paid or incurred in the trade or business of being an artist, the following criteria shall be taken into account: (I)The originality and uniqueness of the item created (or to be created). (II)The predominance of aesthetic value over utilitarian value of the item created (or to be created). (D)Treatment of certain corporations (i)In general If— (I)substantially all of the stock of a corporation is owned by a qualified employee-owner and members of his family (as defined in section 267(c)(4)), and (II)the principal activity of such corporation is performance of personal services directly related to the activities of the qualified employee-owner and such services are substantially performed by the qualified employee-owner, this subsection shall apply to any expense of such corporation which directly relates to the activities of such employee-owner in the same manner as if such expense were incurred by such employee-owner. (ii)Qualified employee-owner For purposes of this subparagraph, the term “qualified employee-owner” means any individual who is an employee-owner of the corporation (as defined in section 269A(b)(2)) and who is a writer, photographer, or artist. (i)Exemption for certain small businesses (1)In general In the case of any taxpayer (other than a tax shelter prohibited from using the cash receipts and disbursements method of accounting under section 448(a)(3)) which meets the gross receipts test of section 448(c) for any taxable year, this section shall not apply with respect to such taxpayer for such taxable year. (2)Application of gross receipts test to individuals, etc. In the case of any taxpayer which is not a corporation or a partnership, the gross receipts test of section 448(c) shall be applied in the same manner as if each trade or business of such taxpayer were a corporation or partnership. (3)Coordination with section 481 Any change in method of accounting made pursuant to this subsection shall be treated for purposes of section 481 as initiated by the taxpayer and made with the consent of the Secretary. (j)Regulations The Secretary shall prescribe such regulations as may be necessary or appropriate to carry out the purposes of this section, including— (1)regulations to prevent the use of related parties, pass-thru entities, or intermediaries to avoid the application of this section, and (2)regulations providing for simplified procedures for the application of this section in the case of property described in subsection (b)(2). (Added Pub. L. 99–514, title VIII, § 803(a), Oct. 22, 1986, 100 Stat. 2350; amended Pub. L. 100–647, title I, § 1008(b)(1)–(4), title VI, § 6026(a)–(c), Nov. 10, 1988, 102 Stat. 3437, 3438, 3691–3693; Pub. L. 101–239, title VII, § 7816(d)(1), Dec. 19, 1989, 103 Stat. 2420; Pub. L. 106–170, title V, § 532(c)(2)(B), Dec. 17, 1999, 113 Stat. 1930; Pub. L. 108–357, title III, § 338(b)(2), Oct. 22, 2004, 118 Stat. 1481; Pub. L. 109–58, title XIII, § 1329(b), Aug. 8, 2005, 119 Stat. 1020; Pub. L. 114–113, div. Q, title I, § 143(b)(6)(H), Dec. 18, 2015, 129 Stat. 3064; Pub. L. 115–97, title I, §§ 13102(b), 13207(a), 13801(a), (b), Dec. 22, 2017, 131 Stat. 2103, 2113, 2169, 2170; Pub. L. 116–94, div. Q, title I, § 144(a)(1), Dec. 20, 2019, 133 Stat. 3234; Pub. L. 116–260, div. EE, title I, § 106(a)(1), Dec. 27, 2020, 134 Stat. 3041; Pub. L. 119–21, title VII, § 70302(b)(7)(B), July 4, 2025, 139 Stat. 192.) | C9: =IFERROR(__xludf.DUMMYFUNCTION("GEMINI(""Summarize IRC §263A in exactly 1 sentence under 20 words. Focus on UNICAP and who it affects. Text: ""&B9)"),"UNICAP requires businesses that produce or acquire property for resale to capitalize direct and certain indirect costs.") -> UNICAP requires businesses that produce or acquire property for resale to capitalize direct and certain indirect costs. | D9: =IFERROR(__xludf.DUMMYFUNCTION("GEMINI(""List 3-5 industries and 2-3 entity types most affected. Format exactly: Industries: [x,y,z] | Entities: [a,b,c]. Text: ""&B9)"),"Industries: [Manufacturing, Wholesale Trade, Retail Trade, Agriculture, Construction] | Entities: [Corporations, Partnerships, Limited Liability Companies]") -> Industries: [Manufacturing, Wholesale Trade, Retail Trade, Agriculture, Construction] | Entities: [Corporations, Partnerships, Limited Liability Companies] | E9: =IFERROR(__xludf.DUMMYFUNCTION("GEMINI(""What QuickBooks data fields check if §263A applies? List comma-separated fields or reports. Text: ""&B9)"),"Cost of Goods Sold, Inventory Asset Accounts, Raw Materials, Work-in-Process, Finished Goods, Direct Labor, Manufacturing Overhead, Purchase Orders, Vendor Invoices, Gross Receipts, Indirect Production Costs (Rent, Utilities, Storage)") -> Cost of Goods Sold, Inventory Asset Accounts, Raw Materials, Work-in-Process, Finished Goods, Direct Labor, Manufacturing Overhead, Purchase Orders, Vendor Invoices, Gross Receipts, Indirect Production Costs (Rent, Utilities, Storage) | F9: 🚨 Important: UNICAP Compliance Update for [Entity] How this affects you: IRC Section 263A (UNICAP) requires your business to capitalize certain direct and indirect costs into inventory or asset basis rather than deducting them as current expenses. If your average annual gross receipts exceed the [Threshold] small business exemption, you must capitalize costs like direct labor, materials, and a share of overhead allocable to produced or resold property. ✅ Identify all direct and indirect production or resale costs for capitalization ✅ Verify if your average annual gross receipts are below the [Threshold] exemption limit ✅ Ensure your QuickBooks Chart of Accounts correctly tracks inventory and capitalized overhead 📚 Source: IRC Section 263A ⚠️ Disclaimer: This template is for informational purposes only. Tax laws are subject to change and individual circumstances vary. Please consult with a qualified tax professional to confirm eligibility and compliance for your specific entity. | G9: =IFERROR(__xludf.DUMMYFUNCTION("GEMINI(""Explain in 1 sentence how §263A impacts cash flow or tax liability. For a non-accountant CFO. Text: ""&B9)"),"IRC Section 263A requires direct and indirect costs to be capitalized rather than expensed, which can increase your taxable income and defer deductions until inventory is sold.") -> IRC Section 263A requires direct and indirect costs to be capitalized rather than expensed, which can increase your taxable income and defer deductions until inventory is sold.
A10: §163(j) | B10: (j)Limitation on business interest (1)In general The amount allowed as a deduction under this chapter for any taxable year for business interest shall not exceed the sum of— (A)the business interest income of such taxpayer for such taxable year, (B)30 percent of the adjusted taxable income of such taxpayer for such taxable year, plus (C)the floor plan financing interest of such taxpayer for such taxable year. The amount determined under subparagraph (B) shall not be less than zero. (2)Carryforward of disallowed business interest The amount of any business interest not allowed as a deduction for any taxable year by reason of paragraph (1) shall be treated as business interest paid or accrued in the succeeding taxable year. (3)Exemption for certain small businesses In the case of any taxpayer (other than a tax shelter prohibited from using the cash receipts and disbursements method of accounting under section 448(a)(3)) which meets the gross receipts test of section 448(c) for any taxable year, paragraph (1) shall not apply to such taxpayer for such taxable year. In the case of any taxpayer which is not a corporation or a partnership, the gross receipts test of section 448(c) shall be applied in the same manner as if such taxpayer were a corporation or partnership. (4)Application to partnerships, etc. (A)In general In the case of any partnership— (i)this subsection shall be applied at the partnership level and any deduction for business interest shall be taken into account in determining the non-separately stated taxable income or loss of the partnership, and (ii)the adjusted taxable income of each partner of such partnership— (I)shall be determined without regard to such partner’s distributive share of any items of income, gain, deduction, or loss of such partnership, and (II)shall be increased by such partner’s distributive share of such partnership’s excess taxable income. For purposes of clause (ii)(II), a partner’s distributive share of partnership excess taxable income shall be determined in the same manner as the partner’s distributive share of nonseparately stated taxable income or loss of the partnership. (B)Special rules for carryforwards (i)In general The amount of any business interest not allowed as a deduction to a partnership for any taxable year by reason of paragraph (1) for any taxable year— (I)shall not be treated under paragraph (2) as business interest paid or accrued by the partnership in the succeeding taxable year, and (II)shall, subject to clause (ii), be treated as excess business interest which is allocated to each partner in the same manner as the non-separately stated taxable income or loss of the partnership. (ii)Treatment of excess business interest allocated to partners If a partner is allocated any excess business interest from a partnership under clause (i) for any taxable year— (I)such excess business interest shall be treated as business interest paid or accrued by the partner in the next succeeding taxable year in which the partner is allocated excess taxable income from such partnership, but only to the extent of such excess taxable income, and (II)any portion of such excess business interest remaining after the application of subclause (I) shall, subject to the limitations of subclause (I), be treated as business interest paid or accrued in succeeding taxable years. For purposes of applying this paragraph, excess taxable income allocated to a partner from a partnership for any taxable year shall not be taken into account under paragraph (1)(A) with respect to any business interest other than excess business interest from the partnership until all such excess business interest for such taxable year and all preceding taxable years has been treated as paid or accrued under clause (ii). (iii)Basis adjustments (I)In general The adjusted basis of a partner in a partnership interest shall be reduced (but not below zero) by the amount of excess business interest allocated to the partner under clause (i)(II). (II)Special rule for dispositions If a partner disposes of a partnership interest, the adjusted basis of the partner in the partnership interest shall be increased immediately before the disposition by the amount of the excess (if any) of the amount of the basis reduction under subclause (I) over the portion of any excess business interest allocated to the partner under clause (i)(II) which has previously been treated under clause (ii) as business interest paid or accrued by the partner. The preceding sentence shall also apply to transfers of the partnership interest (including by reason of death) in a transaction in which gain is not recognized in whole or in part. No deduction shall be allowed to the transferor or transferee under this chapter for any excess business interest resulting in a basis increase under this subclause. (C)Excess taxable income The term “excess taxable income” means, with respect to any partnership, the amount which bears the same ratio to the partnership’s adjusted taxable income as— (i)the excess (if any) of— (I)the amount determined for the partnership under paragraph (1)(B), over (II)the amount (if any) by which the business interest of the partnership, reduced by the floor plan financing interest, exceeds the business interest income of the partnership, bears to (ii)the amount determined for the partnership under paragraph (1)(B). (D)Application to S corporations Rules similar to the rules of subparagraphs (A) and (C) shall apply with respect to any S corporation and its shareholders. (5)Business interest For purposes of this subsection, the term “business interest” means any interest paid or accrued on indebtedness properly allocable to a trade or business. Such term shall not include investment interest (within the meaning of subsection (d)). Such term shall not include any interest which is capitalized under section 263(g) or 263A(f). (6)Business interest income For purposes of this subsection, the term “business interest income” means the amount of interest includible in the gross income of the taxpayer for the taxable year which is properly allocable to a trade or business. Such term shall not include investment income (within the meaning of subsection (d)). (7)Trade or business For purposes of this subsection— (A)In general The term “trade or business” shall not include— (i)the trade or business of performing services as an employee, (ii)any electing real property trade or business, (iii)any electing farming business, or (iv)the trade or business of the furnishing or sale of— (I)electrical energy, water, or sewage disposal services, (II)gas or steam through a local distribution system, or (III)transportation of gas or steam by pipeline, if the rates for such furnishing or sale, as the case may be, have been established or approved by a State or political subdivision thereof, by any agency or instrumentality of the United States, by a public service or public utility commission or other similar body of any State or political subdivision thereof, or by the governing or ratemaking body of an electric cooperative. (B)Electing real property trade or business For purposes of this paragraph, the term “electing real property trade or business” means any trade or business which is described in section 469(c)(7)(C) and which makes an election under this subparagraph. Any such election shall be made at such time and in such manner as the Secretary shall prescribe, and, once made, shall be irrevocable. (C)Electing farming business For purposes of this paragraph, the term “electing farming business” means— (i)a farming business (as defined in section 263A(e)(4)) which makes an election under this subparagraph, or (ii)any trade or business of a specified agricultural or horticultural cooperative (as defined in section 199A(g)(2)) [1] with respect to which the cooperative makes an election under this subparagraph. Any such election shall be made at such time and in such manner as the Secretary shall prescribe, and, once made, shall be irrevocable. (8)Adjusted taxable income For purposes of this subsection, the term “adjusted taxable income” means the taxable income of the taxpayer— (A)computed without regard to— (i)any item of income, gain, deduction, or loss which is not properly allocable to a trade or business, (ii)any business interest or business interest income, (iii)the amount of any net operating loss deduction under section 172, (iv)the amount of any deduction allowed under section 199A, (v)any deduction allowable for depreciation, amortization, or depletion, and (vi)the amounts included in gross income under sections 951(a), 951A(a), and 78 (and the portion of the deductions allowed under sections 245A(a) (by reason of section 964(e)(4)) and 250(a)(1)(B) by reason of such inclusions), and (B)computed with such other adjustments as provided by the Secretary. (9)Floor plan financing interest defined For purposes of this subsection— (A)In general The term “floor plan financing interest” means interest paid or accrued on floor plan financing indebtedness. (B)Floor plan financing indebtedness The term “floor plan financing indebtedness” means indebtedness— (i)used to finance the acquisition of motor vehicles held for sale or lease, and (ii)secured by the inventory so acquired. (C)Motor vehicle The term “motor vehicle” means a motor vehicle that is any of the following: (i)Any self-propelled vehicle designed for transporting persons or property on a public street, highway, or road. (ii)A boat. (iii)Farm machinery or equipment. Such term shall also include any trailer or camper which is designed to provide temporary living quarters for recreational, camping, or seasonal use and is designed to be towed by, or affixed to, a motor vehicle. (10)Coordination with interest capitalization provisions (A)In general In applying this subsection— (i)the limitation under paragraph (1) shall apply to business interest without regard to whether the taxpayer would otherwise deduct such business interest or capitalize such business interest under an interest capitalization provision, and (ii)any reference in this subsection to a deduction for business interest shall be treated as including a reference to the capitalization of business interest. (B)Amount allowed applied first to capitalized interest The amount allowed after taking into account the limitation described in paragraph (1)— (i)shall be applied first to the aggregate amount of business interest which would otherwise be capitalized, and (ii)the remainder (if any) shall be applied to the aggregate amount of business interest which would be deducted. (C)Treatment of disallowed interest carried forward No portion of any business interest carried forward under paragraph (2) from any taxable year to any succeeding taxable year shall, for purposes of this title (including any interest capitalization provision which previously applied to such portion) be treated as interest to which an interest capitalization provision applies. (D)Interest capitalization provision For purposes of this section, the term “interest capitalization provision” means any provision of this subtitle under which interest— (i)is required to be charged to capital account, or (ii)may be deducted or charged to capital account. (11)Regulatory authority The Secretary shall issue such regulations or guidance as may be necessary or appropriate to carry out the purposes of this subsection, including regulations or guidance to determine which business interest is taken into account under this subsection and section 59A(c)(3). (12)Special rule for taxable years beginning in 2019 and 2020 (A)In general (i)In general Except as provided in clause (ii) or (iii), in the case of any taxable year beginning in 2019 or 2020, paragraph (1)(B) shall be applied by substituting “50 percent” for “30 percent”. (ii)Special rule for partnerships In the case of a partnership— (I)clause (i) shall not apply to any taxable year beginning in 2019, but (II)unless a partner elects not to have this subclause apply, in the case of any excess business interest of the partnership for any taxable year beginning in 2019 which is allocated to the partner under paragraph (4)(B)(i)(II)— (aa)50 percent of such excess business interest shall be treated as business interest which, notwithstanding paragraph (4)(B)(ii), is paid or accrued by the partner in the partner’s first taxable year beginning in 2020 and which is not subject to the limits of paragraph (1), and (bb)50 percent of such excess business interest shall be subject to the limitations of paragraph (4)(B)(ii) in the same manner as any other excess business interest so allocated. (iii)Election out A taxpayer may elect, at such time and in such manner as the Secretary may prescribe, not to have clause (i) apply to any taxable year. Such an election, once made, may be revoked only with the consent of the Secretary. In the case of a partnership, any such election shall be made by the partnership and may be made only for taxable years beginning in 2020. (B)Election to use 2019 adjusted taxable income for taxable years beginning in 2020 (i)In general Subject to clause (ii), in the case of any taxable year beginning in 2020, the taxpayer may elect to apply this subsection by substituting the adjusted taxable income of the taxpayer for the last taxable year beginning in 2019 for the adjusted taxable income for such taxable year. In the case of a partnership, any such election shall be made by the partnership. (ii)Special rule for short taxable years If an election is made under clause (i) for a taxable year which is a short taxable year, the adjusted taxable income for the taxpayer’s last taxable year beginning in 2019 which is substituted under clause (i) shall be equal to the amount which bears the same ratio to such adjusted taxable income determined without regard to this clause as the number of months in the short taxable year bears to 12 [2] (13)Cross references (A)For requirement that an electing real property trade or business use the alternative depreciation system, see section 168(g)(1)(F). (B)For requirement that an electing farming business use the alternative depreciation system, see section 168(g)(1)(G). | C10: =IFERROR(__xludf.DUMMYFUNCTION("GEMINI(""Summarize IRC §163(j) in exactly 1 sentence under 20 words. Focus on the 30% EBITDA interest deduction limit. Text: ""&B10)"),"IRC Section 163(j) limits business interest deductions to 30% of adjusted taxable income plus business interest income.") -> IRC Section 163(j) limits business interest deductions to 30% of adjusted taxable income plus business interest income. | D10: =IFERROR(__xludf.DUMMYFUNCTION("GEMINI(""List 3-5 industries and 2-3 entity types most affected. Format exactly: Industries: [x,y,z] | Entities: [a,b,c]. Text: ""&B10)"),"Industries: [Automotive, Agriculture, Real Estate, Manufacturing, Finance] | Entities: [Corporations, Partnerships, S Corporations]") -> Industries: [Automotive, Agriculture, Real Estate, Manufacturing, Finance] | Entities: [Corporations, Partnerships, S Corporations] | E10: =IFERROR(__xludf.DUMMYFUNCTION("GEMINI(""What QuickBooks data fields check if §163(j) applies? List comma-separated interest expense, loan balance, or EBITDA fields. Text: ""&B10)"),"Interest Expense, Interest Income, Floor Plan Financing Interest, Gross Receipts (for 3-year average test), Net Income (Profit & Loss), Depreciation, Amortization, Depletion, Net Operating Loss (NOL), Section 199A Deduction, Interest Capitalized to Assets"&", Loan Balance/Debt Liabilities, EBITDA/ATI Adjustments") -> Interest Expense, Interest Income, Floor Plan Financing Interest, Gross Receipts (for 3-year average test), Net Income (Profit & Loss), Depreciation, Amortization, Depletion, Net Operating Loss (NOL), Section 199A Deduction, Interest Capitalized to Assets, Loan Balance/Debt Liabilities, EBITDA/ATI Adjustments | F10: 🚨 Important: Business Interest Deduction Update for [Entity] How this affects you: Based on your [Interest_Expense] and [EBITDA], your business interest deduction is generally limited to 30% of your adjusted taxable income. We estimate your current deduction limit at [Deduction_Limit], with a potential \[Disallowed\_Amount\] to be carried forward. This carryforward note ensures that any disallowed interest is not lost but can be treated as an expense in succeeding taxable years. ✅ Review your [EBITDA] and adjusted taxable income calculations for accuracy ✅ Implement a system for detailed interest tracking to manage carryforwards ✅ Consult with a CPA to evaluate debt structuring or potential elections 📚 Source: IRC Section 163(j) ⚠️ Disclaimer: This template is for informational purposes only. Tax laws are subject to change and individual circumstances vary. Please consult with a qualified tax professional to confirm eligibility and compliance for your specific entity. | G10: =IFERROR(__xludf.DUMMYFUNCTION("GEMINI(""Explain in 1 sentence how §163(j) impacts Interest Coverage or Debt-to-EBITDA ratios. For a non-accountant CFO. Text: ""&B10)"),"IRC Section 163(j) limits the tax deductibility of interest to 30% of adjusted taxable income, which can lower your interest coverage ratio and increase your after-tax debt-to-EBITDA costs by reducing the cash flow benefit of debt.") -> IRC Section 163(j) limits the tax deductibility of interest to 30% of adjusted taxable income, which can lower your interest coverage ratio and increase your after-tax debt-to-EBITDA costs by reducing the cash flow benefit of debt.
A11: §274 | B11: (a)Entertainment, amusement, recreation, or qualified transportation fringes (1)In general No deduction otherwise allowable under this chapter shall be allowed for any item— (A)Activity With respect to an activity which is of a type generally considered to constitute entertainment, amusement, or recreation, or (B)Facility With respect to a facility used in connection with an activity referred to in subparagraph (A). (2)Special rules For purposes of applying paragraph (1)— (A)Dues or fees to any social, athletic, or sporting club or organization shall be treated as items with respect to facilities. (B)An activity described in section 212 shall be treated as a trade or business. (3)Denial of deduction for club dues Notwithstanding the preceding provisions of this subsection, no deduction shall be allowed under this chapter for amounts paid or incurred for membership in any club organized for business, pleasure, recreation, or other social purpose. (4)Qualified transportation fringes No deduction shall be allowed under this chapter for the expense of any qualified transportation fringe (as defined in section 132(f)) provided to an employee of the taxpayer. (b)Gifts (1)Limitation No deduction shall be allowed under section 162 or section 212 for any expense for gifts made directly or indirectly to any individual to the extent that such expense, when added to prior expenses of the taxpayer for gifts made to such individual during the same taxable year, exceeds $25. For purposes of this section, the term “gift” means any item excludable from gross income of the recipient under section 102 which is not excludable from his gross income under any other provision of this chapter, but such term does not include— (A)an item having a cost to the taxpayer not in excess of $4.00 on which the name of the taxpayer is clearly and permanently imprinted and which is one of a number of identical items distributed generally by the taxpayer, or (B)a sign, display rack, or other promotional material to be used on the business premises of the recipient. (2)Special rules (A)In the case of a gift by a partnership, the limitation contained in paragraph (1) shall apply to the partnership as well as to each member thereof. (B)For purposes of paragraph (1), a husband and wife shall be treated as one taxpayer. (c)Certain foreign travel (1)In general In the case of any individual who travels outside the United States away from home in pursuit of a trade or business or in pursuit of an activity described in section 212, no deduction shall be allowed under section 162 or section 212 for that portion of the expenses of such travel otherwise allowable under such section which, under regulations prescribed by the Secretary, is not allocable to such trade or business or to such activity. (2)Exception Paragraph (1) shall not apply to the expenses of any travel outside the United States away from home if— (A)such travel does not exceed one week, or (B)the portion of the time of travel outside the United States away from home which is not attributable to the pursuit of the taxpayer’s trade or business or an activity described in section 212 is less than 25 percent of the total time on such travel. (3)Domestic travel excluded For purposes of this subsection, travel outside the United States does not include any travel from one point in the United States to another point in the United States. (d)Substantiation required No deduction or credit shall be allowed— (1)under section 162 or 212 for any traveling expense (including meals and lodging while away from home), (2)for any expense for gifts, or (3)with respect to any listed property (as defined in section 280F(d)(4)), unless the taxpayer substantiates by adequate records or by sufficient evidence corroborating the taxpayer’s own statement (A) the amount of such expense or other item, (B) the time and place of the travel or the date and description of the gift, (C) the business purpose of the expense or other item, and (D) the business relationship to the taxpayer of the person receiving the benefit. The Secretary may by regulations provide that some or all of the requirements of the preceding sentence shall not apply in the case of an expense which does not exceed an amount prescribed pursuant to such regulations. This subsection shall not apply to any qualified nonpersonal use vehicle (as defined in subsection (i)). (e)Specific exceptions to application of subsection (a) Subsection (a) shall not apply to— (1)Food and beverages for employees Expenses for food and beverages (and facilities used in connection therewith) furnished on the business premises of the taxpayer primarily for his employees. (2)Expenses treated as compensation (A)In general Except as provided in subparagraph (B), expenses for goods, services, and facilities, to the extent that the expenses are treated by the taxpayer, with respect to the recipient of the entertainment, amusement, or recreation, as compensation to an employee on the taxpayer’s return of tax under this chapter and as wages to such employee for purposes of chapter 24 (relating to withholding of income tax at source on wages). (B)Specified individuals (i)In general In the case of a recipient who is a specified individual, subparagraph (A) and paragraph (9) shall each be applied by substituting “to the extent that the expenses do not exceed the amount of the expenses which” for “to the extent that the expenses”. (ii)Specified individual For purposes of clause (i), the term “specified individual” means any individual who— (I)is subject to the requirements of section 16(a) of the Securities Exchange Act of 1934 with respect to the taxpayer or a related party to the taxpayer, or (II)would be subject to such requirements if the taxpayer (or such related party) were an issuer of equity securities referred to in such section. For purposes of this clause, a person is a related party with respect to another person if such person bears a relationship to such other person described in section 267(b) or 707(b). (3)Reimbursed expenses Expenses paid or incurred by the taxpayer, in connection with the performance by him of services for another person (whether or not such other person is his employer), under a reimbursement or other expense allowance arrangement with such other person, but this paragraph shall apply— (A)where the services are performed for an employer, only if the employer has not treated such expenses in the manner provided in paragraph (2), or (B)where the services are performed for a person other than an employer, only if the taxpayer accounts (to the extent provided by subsection (d)) to such person. (4)Recreational, etc., expenses for employees Expenses for recreational, social, or similar activities (including facilities therefor) primarily for the benefit of employees (other than employees who are highly compensated employees (within the meaning of section 414(q))). For purposes of this paragraph, an individual owning less than a 10-percent interest in the taxpayer’s trade or business shall not be considered a shareholder or other owner, and for such purposes an individual shall be treated as owning any interest owned by a member of his family (within the meaning of section 267(c)(4)). This paragraph shall not apply for purposes of subsection (a)(3). (5)Employees, stockholder, etc., business meetings Expenses incurred by a taxpayer which are directly related to business meetings of his employees, stockholders, agents, or directors. (6)Meetings of business leagues, etc. Expenses directly related and necessary to attendance at a business meeting or convention of any organization described in section 501(c)(6) (relating to business leagues, chambers of commerce, real estate boards, and boards of trade) and exempt from taxation under section 501(a). (7)Items available to public Expenses for goods, services, and facilities made available by the taxpayer to the general public. (8)Entertainment sold to customers Expenses for goods or services (including the use of facilities) which are sold by the taxpayer in a bona fide transaction for an adequate and full consideration in money or money’s worth. (9)Expenses includible in income of persons who are not employees Expenses paid or incurred by the taxpayer for goods, services, and facilities to the extent that the expenses are includible in the gross income of a recipient of the entertainment, amusement, or recreation who is not an employee of the taxpayer as compensation for services rendered or as a prize or award under section 74. The preceding sentence shall not apply to any amount paid or incurred by the taxpayer if such amount is required to be included (or would be so required except that the amount is less than $600) in any information return filed by such taxpayer under part III of subchapter A of chapter 61 and is not so included. For purposes of this subsection, any item referred to in subsection (a) shall be treated as an expense. (f)Interest, taxes, casualty losses, etc. This section shall not apply to any deduction allowable to the taxpayer without regard to its connection with his trade or business (or with his income-producing activity). In the case of a taxpayer which is not an individual, the preceding sentence shall be applied as if it were an individual. (g)Treatment of entertainment, etc., type facility For purposes of this chapter, if deductions are disallowed under subsection (a) with respect to any portion of a facility, such portion shall be treated as an asset which is used for personal, living, and family purposes (and not as an asset used in the trade or business). (h)Attendance at conventions, etc. (1)In general In the case of any individual who attends a convention, seminar, or similar meeting which is held outside the North American area, no deduction shall be allowed under section 162 for expenses allocable to such meeting unless the taxpayer establishes that the meeting is directly related to the active conduct of his trade or business and that, after taking into account in the manner provided by regulations prescribed by the Secretary— (A)the purpose of such meeting and the activities taking place at such meeting, (B)the purposes and activities of the sponsoring organizations or groups, (C)the residences of the active members of the sponsoring organization and the places at which other meetings of the sponsoring organization or groups have been held or will be held, and (D)such other relevant factors as the taxpayer may present, it is as reasonable for the meeting to be held outside the North American area as within the North American area. (2)Conventions on cruise ships In the case of any individual who attends a convention, seminar, or other meeting which is held on any cruise ship, no deduction shall be allowed under section 162 for expenses allocable to such meeting, unless the taxpayer meets the requirements of paragraph (5) and establishes that the meeting is directly related to the active conduct of his trade or business and that— (A)the cruise ship is a vessel registered in the United States; and (B)all ports of call of such cruise ship are located in the United States or in possessions of the United States. With respect to cruises beginning in any calendar year, not more than $2,000 of the expenses attributable to an individual attending one or more meetings may be taken into account under section 162 by reason of the preceding sentence. (3)Definitions For purposes of this subsection— (A)North American area The term “North American area” means the United States, its possessions, and the Trust Territory of the Pacific Islands, and Canada and Mexico. (B)Cruise ship The term “cruise ship” means any vessel sailing within or without the territorial waters of the United States. (4)Subsection to apply to employer as well as to traveler (A)Except as provided in subparagraph (B), this subsection shall apply to deductions otherwise allowable under section 162 to any person, whether or not such person is the individual attending the convention, seminar, or similar meeting. (B)This subsection shall not deny a deduction to any person other than the individual attending the convention, seminar, or similar meeting with respect to any amount paid by such person to or on behalf of such individual if includible in the gross income of such individual. The preceding sentence shall not apply if the amount is required to be included in any information return filed by such person under part III of subchapter A of chapter 61 and is not so included. (5)Reporting requirements No deduction shall be allowed under section 162 for expenses allocable to attendance at a convention, seminar, or similar meeting on any cruise ship unless the taxpayer claiming the deduction attaches to the return of tax on which the deduction is claimed— (A)a written statement signed by the individual attending the meeting which includes— (i)information with respect to the total days of the trip, excluding the days of transportation to and from the cruise ship port, and the number of hours of each day of the trip which such individual devoted to scheduled business activities, (ii)a program of the scheduled business activities of the meeting, and (iii)such other information as may be required in regulations prescribed by the Secretary; and (B)a written statement signed by an officer of the organization or group sponsoring the meeting which includes— (i)a schedule of the business activities of each day of the meeting, (ii)the number of hours which the individual attending the meeting attended such scheduled business activities, and (iii)such other information as may be required in regulations prescribed by the Secretary. (6)Treatment of conventions in certain Caribbean countries (A)In general For purposes of this subsection, the term “North American area” includes, with respect to any convention, seminar, or similar meeting, any beneficiary country if (as of the time such meeting begins)— (i)there is in effect a bilateral or multilateral agreement described in subparagraph (C) between such country and the United States providing for the exchange of information between the United States and such country, and (ii)there is not in effect a finding by the Secretary that the tax laws of such country discriminate against conventions held in the United States. (B)Beneficiary country For purposes of this paragraph, the term “beneficiary country” has the meaning given to such term by section 212(a)(1)(A) of the Caribbean Basin Economic Recovery Act; except that such term shall include Bermuda. (C)Authority to conclude exchange of information agreements (i)In general The Secretary is authorized to negotiate and conclude an agreement for the exchange of information with any beneficiary country. Except as provided in clause (ii), an exchange of information agreement shall provide for the exchange of such information (not limited to information concerning nationals or residents of the United States or the beneficiary country) as may be necessary or appropriate to carry out and enforce the tax laws of the United States and the beneficiary country (whether criminal or civil proceedings), including information which may otherwise be subject to nondisclosure provisions of the local law of the beneficiary country such as provisions respecting bank secrecy and bearer shares. The exchange of information agreement shall be terminable by either country on reasonable notice and shall provide that information received by either country will be disclosed only to persons or authorities (including courts and administrative bodies) involved in the administration or oversight of, or in the determination of appeals in respect of, taxes of the United States or the beneficiary country and will be used by such persons or authorities only for such purposes. (ii)Nondisclosure of qualified confidential information sought for civil tax purposes An exchange of information agreement need not provide for the exchange of qualified confidential information which is sought only for civil tax purposes if— (I)the Secretary of the Treasury, after making all reasonable efforts to negotiate an agreement which includes the exchange of such information, determines that such an agreement cannot be negotiated but that the agreement which was negotiated will significantly assist in the administration and enforcement of the tax laws of the United States, and (II)the President determines that the agreement as negotiated is in the national security interest of the United States. (iii)Qualified confidential information defined For purposes of this subparagraph, the term “qualified confidential information” means information which is subject to the nondisclosure provisions of any local law of the beneficiary country regarding bank secrecy or ownership of bearer shares. (iv)Civil tax purposes For purposes of this subparagraph, the determination of whether information is sought only for civil tax purposes shall be made by the requesting party. (D)Coordination with other provisions Any exchange of information agreement negotiated under subparagraph (C) shall be treated as an income tax convention for purposes of section 6103(k)(4). The Secretary may exercise his authority under subchapter A of chapter 78 to carry out any obligation of the United States under an agreement referred to in subparagraph (C). (E)Determinations published in the Federal Register The following shall be published in the Federal Register— (i)any determination by the President under subparagraph (C)(ii) (including the reasons for such determination), (ii)any determination by the Secretary under subparagraph (C)(ii) (including the reasons for such determination), and (iii)any finding by the Secretary under subparagraph (A)(ii) (and any termination thereof). (7)Seminars, etc. for section 212 purposes No deduction shall be allowed under section 212 for expenses allocable to a convention, seminar, or similar meeting. (i)Qualified nonpersonal use vehicle For purposes of subsection (d), the term “qualified nonpersonal use vehicle” means any vehicle which, by reason of its nature, is not likely to be used more than a de minimis amount for personal purposes. (j)Employee achievement awards (1)General rule No deduction shall be allowed under section 162 or section 212 for the cost of an employee achievement award except to the extent that such cost does not exceed the deduction limitations of paragraph (2). (2)Deduction limitations The deduction for the cost of an employee achievement award made by an employer to an employee— (A)which is not a qualified plan award, when added to the cost to the employer for all other employee achievement awards made to such employee during the taxable year which are not qualified plan awards, shall not exceed $400, and (B)which is a qualified plan award, when added to the cost to the employer for all other employee achievement awards made to such employee during the taxable year (including employee achievement awards which are not qualified plan awards), shall not exceed $1,600. (3)Definitions For purposes of this subsection— (A)Employee achievement award (i)In general The term “employee achievement award” means an item of tangible personal property which is— (I)transferred by an employer to an employee for length of service achievement or safety achievement, (II)awarded as part of a meaningful presentation, and (III)awarded under conditions and circumstances that do not create a significant likelihood of the payment of disguised compensation. (ii)Tangible personal property For purposes of clause (i), the term “tangible personal property” shall not include— (I)cash, cash equivalents, gift cards, gift coupons, or gift certificates (other than arrangements conferring only the right to select and receive tangible personal property from a limited array of such items pre-selected or pre-approved by the employer), or (II)vacations, meals, lodging, tickets to theater or sporting events, stocks, bonds, other securities, and other similar items. (B)Qualified plan award (i)In general The term “qualified plan award” means an employee achievement award awarded as part of an established written plan or program of the taxpayer which does not discriminate in favor of highly compensated employees (within the meaning of section 414(q)) as to eligibility or benefits. (ii)Limitation An employee achievement award shall not be treated as a qualified plan award for any taxable year if the average cost of all employee achievement awards which are provided by the employer during the year, and which would be qualified plan awards but for this subparagraph, exceeds $400. For purposes of the preceding sentence, average cost shall be determined by including the entire cost of qualified plan awards, without taking into account employee achievement awards of nominal value. (4)Special rules For purposes of this subsection— (A)Partnerships In the case of an employee achievement award made by a partnership, the deduction limitations contained in paragraph (2) shall apply to the partnership as well as to each member thereof. (B)Length of service awards An item shall not be treated as having been provided for length of service achievement if the item is received during the recipient’s 1st 5 years of employment or if the recipient received a length of service achievement award (other than an award excludable under section 132(e)(1)) during that year or any of the prior 4 years. (C)Safety achievement awards An item provided by an employer to an employee shall not be treated as having been provided for safety achievement if— (i)during the taxable year, employee achievement awards (other than awards excludable under section 132(e)(1)) for safety achievement have previously been awarded by the employer to more than 10 percent of the employees of the employer (excluding employees described in clause (ii)), or (ii)such item is awarded to a manager, administrator, clerical employee, or other professional employee. (k)Business meals (1)In general No deduction shall be allowed under this chapter for the expense of any food or beverages unless— (A)such expense is not lavish or extravagant under the circumstances, and (B)the taxpayer (or an employee of the taxpayer) is present at the furnishing of such food or beverages. (2)Exceptions Paragraph (1) shall not apply to— (A)any expense described in paragraph (2), (3), (4), (7), (8), or (9) of subsection (e), and (B)any other expense to the extent provided in regulations. (l)Transportation and commuting benefits No deduction shall be allowed under this chapter for any expense incurred for providing any transportation, or any payment or reimbursement, to an employee of the taxpayer in connection with travel between the employee’s residence and place of employment, except as necessary for ensuring the safety of the employee. (m)Additional limitations on travel expenses (1)Luxury water transportation (A)In general No deduction shall be allowed under this chapter for expenses incurred for transportation by water to the extent such expenses exceed twice the aggregate per diem amounts for days of such transportation. For purposes of the preceding sentence, the term “per diem amounts” means the highest amount generally allowable with respect to a day to employees of the executive branch of the Federal Government for per diem while away from home but serving in the United States. (B)Exceptions Subparagraph (A) shall not apply to— (i)any expense allocable to a convention, seminar, or other meeting which is held on any cruise ship, and (ii)any expense described in paragraph (2), (3), (4), (7), (8), or (9) of subsection (e). (2)Travel as form of education No deduction shall be allowed under this chapter for expenses for travel as a form of education. (3)Travel expenses of spouse, dependent, or others No deduction shall be allowed under this chapter (other than section 217) for travel expenses paid or incurred with respect to a spouse, dependent, or other individual accompanying the taxpayer (or an officer or employee of the taxpayer) on business travel, unless— (A)the spouse, dependent, or other individual is an employee of the taxpayer, (B)the travel of the spouse, dependent, or other individual is for a bona fide business purpose, and (C)such expenses would otherwise be deductible by the spouse, dependent, or other individual. (n)Only 50 percent of meal expenses allowed as deduction (1)In general The amount allowable as a deduction under this chapter for any expense for food or beverages shall not exceed 50 percent of the amount of such expense which would (but for this paragraph) be allowable as a deduction under this chapter. (2)Exceptions Paragraph (1) shall not apply to any expense if— (A)such expense is described in paragraph (2), (3), (4), (7), (8), or (9) of subsection (e), (B)in the case of an employer who pays or reimburses moving expenses of an employee, such expenses are includible in the income of the employee under section 82, (C)such expense is for food or beverages— (i)required by any Federal law to be provided to crew members of a commercial vessel, (ii)provided to crew members of a commercial vessel— (I)which is operating on the Great Lakes, the Saint Lawrence Seaway, or any inland waterway of the United States, and (II)which is of a kind which would be required by Federal law to provide food and beverages to crew members if it were operated at sea, (iii)provided on an oil or gas platform or drilling rig if the platform or rig is located offshore, (iv)provided on an oil or gas platform or drilling rig, or at a support camp which is in proximity and integral to such platform or rig, if the platform or rig is located in the United States north of 54 degrees north latitude, or (v)provided— (I)on a fishing vessel, fish processing vessel, or fish tender vessel (as such terms are defined in section 2101 of title 46, United States Code), or (II)at a facility for the processing of fish for commercial use or consumption which— (aa)is located in the United States north of 50 degrees north latitude, and (bb)is not located in a metropolitan statistical area (within the meaning of section 143(k)(2)(B)), or (D)such expense is— (i)for food or beverages provided by a restaurant, and (ii)paid or incurred before January 1, 2023. Clauses (i) and (ii) of subparagraph (C) shall not apply to vessels primarily engaged in providing luxury water transportation (determined under the principles of subsection (m)). In the case of the employee, the exception of subparagraph (A) shall not apply to expenses described in subparagraph (B). (3)Special rule for individuals subject to Federal hours of service In the case of any expenses for food or beverages consumed while away from home (within the meaning of section 162(a)(2)) by an individual during, or incident to, the period of duty subject to the hours of service limitations of the Department of Transportation, paragraph (1) shall be applied by substituting “80 percent” for “50 percent”. (o)Meals provided at convenience of employer Except in the case of an expense described in subsection (e)(8) or (n)(2)(C), no deduction shall be allowed under this chapter for— (1)any expense for the operation of a facility described in section 132(e)(2), and any expense for food or beverages, including under section 132(e)(1), associated with such facility, or (2)any expense for meals described in section 119(a). (p)Regulatory authority The Secretary shall prescribe such regulations as he may deem necessary to carry out the purposes of this section, including regulations prescribing whether subsection (a) or subsection (b) applies in cases where both such subsections would otherwise apply. (Added Pub. L. 87–834, § 4(a)(1), Oct. 16, 1962, 76 Stat. 974; amended Pub. L. 88–272, title II, § 217(a), Feb. 26, 1964, 78 Stat. 56; Pub. L. 94–455, title VI, § 602(a), title XIX, § 1906(b)(13)(A), Oct. 4, 1976, 90 Stat. 1572, 1834; Pub. L. 95–600, title III, § 361(a), (b), title VII, § 701(g)(1)–(3), Nov. 6, 1978, 92 Stat. 2847, 2903, 2904; Pub. L. 96–222, title I, § 103(a)(10)(A), (B) Apr. 1, 1980, 94 Stat. 212; Pub. L. 96–598, § 5(a), Dec. 24, 1980, 94 Stat. 3488; Pub. L. 96–605, title I, § 108(a), Dec. 28, 1980, 94 Stat. 3524; Pub. L. 96–608, § 4(a), Dec. 28, 1980, 94 Stat. 3552; Pub. L. 97–34, title II, § 265(a), (b), Aug. 13, 1981, 95 Stat. 265; Pub. L. 97–248, title III, §§ 307(a)(1), 308(a), Sept. 3, 1982, 96 Stat. 589, 591; Pub. L. 97–424, title V, § 543(a), Jan. 6, 1983, 96 Stat. 2195; Pub. L. 98–67, title I, § 102(a), title II, § 222(a), Aug. 5, 1983, 97 Stat. 369, 395; Pub. L. 98–369, div. A, title I, § 179(b)(1), title VIII, § 801(c), July 18, 1984, 98 Stat. 718, 995; Pub. L. 99–44, §§ 1(a), 2, 6(b), May 24, 1985, 99 Stat. 77, 79; Pub. L. 99–514, title I, §§ 122(c), (d), 142(a)–(c), title XI, § 1114(b)(6), Oct. 22, 1986, 100 Stat. 2110, 2117–2120, 2451; Pub. L. 100–647, title I, §§ 1001(g)(1)–(4)(A), (5), 1018(u)(2), title VI, § 6003(a), Nov. 10, 1988, 102 Stat. 3351, 3352, 3590, 3684; Pub. L. 101–239, title VII, §§ 7816(a), 7841(d)(18), Dec. 19, 1989, 103 Stat. 2420, 2429; Pub. L. 101–508, title XI, § 11802(b), Nov. 5, 1990, 104 Stat. 1388–529; Pub. L. 103–66, title XIII, §§ 13209(a), (b), 13210(a), (b), 13272(a), Aug. 10, 1993, 107 Stat. 469, 542; Pub. L. 105–34, title IX, § 969(a), Aug. 5, 1997, 111 Stat. 896; Pub. L. 108–357, title VIII, § 907(a), Oct. 22, 2004, 118 Stat. 1654; Pub. L. 109–135, title IV, § 403(mm), Dec. 21, 2005, 119 Stat. 2632; Pub. L. 113–295, div. A, title II, § 221(a)(46), Dec. 19, 2014, 128 Stat. 4045; Pub. L. 115–97, title I, §§ 13304(a)(1)–(2)(E), (b)–(d), 13310(a), Dec. 22, 2017, 131 Stat. 2124–2126, 2132; Pub. L. 116–260, div. EE, title II, § 210(a), Dec. 27, 2020, 134 Stat. 3066; Pub. L. 119–21, title VII, §§ 70112(c), 70305(a), (b), July 4, 2025, 139 Stat. 165, 197.) | C11: =IFERROR(__xludf.DUMMYFUNCTION("GEMINI(""Summarize IRC §274 in exactly 1 sentence under 20 words. Focus on 50% meal limit and entertainment nondeductibility. Text: ""&B11)"),"IRC Section 274 generally disallows deductions for entertainment expenses while limiting business meal deductions to 50 percent.") -> IRC Section 274 generally disallows deductions for entertainment expenses while limiting business meal deductions to 50 percent. | D11: =IFERROR(__xludf.DUMMYFUNCTION("GEMINI(""List 3-5 industries and 2-3 entity types most affected. Format exactly: Industries: [x,y,z] | Entities: [a,b,c]. Text: ""&B11)"),"Industries: [Hospitality, Travel, Entertainment, Food and Beverage, Professional Services] | Entities: [Corporations, Partnerships, Limited Liability Companies, Sole Proprietorships]") -> Industries: [Hospitality, Travel, Entertainment, Food and Beverage, Professional Services] | Entities: [Corporations, Partnerships, Limited Liability Companies, Sole Proprietorships] | E11: =IFERROR(__xludf.DUMMYFUNCTION("GEMINI(""What QuickBooks data fields check if §274 applies? List comma-separated meal, travel, entertainment expense accounts. Text: ""&B11)"),"Travel Expense, Meals Expense, Entertainment Expense, Gifts, Automobile Expense, Lodging, Transportation, Chart of Accounts, General Ledger, Vendor Invoices, Receipts, Expense Reports") -> Travel Expense, Meals Expense, Entertainment Expense, Gifts, Automobile Expense, Lodging, Transportation, Chart of Accounts, General Ledger, Vendor Invoices, Receipts, Expense Reports | F11: 🚨 Important: Business Meal and Entertainment Deduction Update for [Entity] How this affects you: Beginning in 2026, tax laws regarding meals and entertainment have tightened. While business meals with clients remain 50% deductible, most employer-provided meals (like on-site snacks or cafeteria food) are now nondeductible. Based on your current [Meal_Expense], we estimate your [Deductible_Amount] and [NonDeductible_Amount]. Note that entertainment activities—such as sporting events, golf, or club dues—remain 100% nondeductible even if they have a business purpose. ✅ Maintain detailed records for each meal, including the business purpose, relationship of attendees, date, and location to substantiate the 50% deduction ✅ Review and update your internal reimbursement policies to reflect the total loss of deductions for employer-provided convenience meals ✅ Tag all food and beverage expenses in QuickBooks by class or category to distinguish between 50% deductible travel/client meals and nondeductible entertainment 📚 Source: IRC Section 274 ⚠️ Disclaimer: This template is for informational purposes only. Tax laws are subject to change and individual circumstances vary. Please consult with a qualified tax professional to confirm eligibility and compliance for your specific entity. | G11: =IFERROR(__xludf.DUMMYFUNCTION("GEMINI(""Explain in 1 sentence how §274 impacts Operating Expense or Effective Tax Rate ratios. For a non-accountant CFO. Text: ""&B11)"),"IRC Section 274 increases your effective tax rate by disallowing deductions for entertainment and limiting business meal deductions, thereby raising taxable income without increasing cash flow.") -> IRC Section 274 increases your effective tax rate by disallowing deductions for entertainment and limiting business meal deductions, thereby raising taxable income without increasing cash flow.
